{
  "classname": null,
  "name": null,
  "animation": {
    "classname": null,
    "name": "AnimationManager",
    "actionlist": []
  },
  "dataScale": 1,
  "designHeight": 960,
  "designWidth": 640,
  "textures": [],
  "texturesPng": [
    "common/head_bg.png",
    "common/building_bg.png",
    "building/farm_1.png",
    "common/progress1_bg.png",
    "common/progress1.png",
    "common/button_red.png",
    "common/button_green.png",
    "common/desc_bg.png",
    "common/line2_center.png",
    "common/line2_left.png",
    "common/line2_right.png",
    "building/farm_1.png",
    "common/building_name_bg.png",
    "common/notopen.png",
    "common/head_bg.png",
    "common/building_bg.png",
    "building/farm_1.png",
    "common/progress1_bg.png",
    "common/progress1.png",
    "common/button_blue.png",
    "common/gold_bg.png",
    "common/gold.png",
    "common/button_green.png",
    "common/desc_bg.png",
    "common/title_desc_bg.png",
    "common/line2_center.png",
    "common/line2_left.png",
    "common/line2_right.png",
    "common/build_icon2.png",
    "common/wrong.png",
    "common/food_big.png",
    "common/right.png",
    "common/heroxp.png",
    "common/button_green.png",
    "common/copy_icon.png",
    "headpic/02.png",
    "common/pageTurn1.png",
    "common/button_red.png",
    "common/button_green.png",
    "common/chaticon_addFriend.png",
    "common/chaticon_mail.png",
    "headpic/02.png",
    "common/block_icon.png",
    "common/button_red.png",
    "common/frame_bg.png",
    "common/frame_border_left.png",
    "common/frame_border_right.png",
    "common/frame_bg_head.png",
    "common/alliance_17.png",
    "common/line_center.png",
    "common/line_left.png",
    "common/line_right.png",
    "common/frame_border_top.png",
    "common/button_green1.png",
    "common/list_icon.png",
    "common/close_icon.png",
    "common/btn_tab.png",
    "common/chat.png",
    "common/setting_icon.png",
    "common/common_bg2.png",
    "common/quest_25.png",
    "common/title_bg2.png",
    "common/chaticon_friends.png",
    "common/num_bg1.png",
    "common/chaticon_addFriend.png",
    "common/chaticon_wait.png",
    "common/ui_barrack_line_hor.png",
    "common/online_icon.png",
    "common/button_red.png",
    "common/alliance_17.png",
    "common/line_center.png",
    "common/line_left.png",
    "common/line_right.png",
    "common/editbox_bg.png",
    "common/button_green1.png",
    "common/chat_icon.png",
    "common/bg_1.png",
    "common/bg_2.png",
    "common/bg_3.png",
    "common/bg_4.png",
    "common/bg_5.png",
    "common/bg_6.png",
    "common/bg_7.png",
    "common/bg_8.png",
    "common/bg_9.png",
    "common/chat_point.png",
    "headpic/02.png",
    "common/head_frame.png",
    "common/vip_rank_03.png",
    "common/quest_5.png",
    "common/bg_1.png",
    "common/bg_2.png",
    "common/bg_3.png",
    "common/bg_4.png",
    "common/bg_5.png",
    "common/bg_6.png",
    "common/bg_7.png",
    "common/bg_8.png",
    "common/bg_9.png",
    "common/chat_point.png",
    "headpic/02.png",
    "common/head_frame.png",
    "common/button_blue1.png",
    "common/button_red1.png",
    "common/line2_center.png",
    "common/line2_left.png",
    "common/line2_right.png",
    "common/editbox_bg.png",
    "common/button_gray.png",
    "common/main_bg_res.png",
    "common/main_bg_head.png",
    "heroHeadpic/02.png",
    "common/photo_frame.png",
    "common/progress_exp.png",
    "common/main_vip_btn.png",
    "common/title_bg.png",
    "common/gold_frame.png",
    "common/add_gold.png",
    "common/rock.png",
    "common/wood.png",
    "common/mine.png",
    "common/food.png",
    "common/silver.png",
    "common/common_bg1.png",
    "common/pageTurn.png",
    "common/name_bg.png",
    "common/box_golden.png",
    "common/box_silvery.png",
    "common/gold1.png",
    "common/translucence_bg.png",
    "common/progress_bg.png",
    "common/ui_hero_progress.png",
    "common/ui_hero_progressHigh.png",
    "common/quest_6.png",
    "common/build_icon.png",
    "common/button_blue1.png",
    "common/special_bg.png",
    "common/smith_combine_bg.png",
    "common/common_bg.png",
    "common/line_center.png",
    "common/line_left.png",
    "common/line_right.png",
    "common/btn_tab.png",
    "common/gem_icon.png",
    "common/material_icon.png",
    "common/colorframe_3.png",
    "material/5.png",
    "common/pageTurn1.png",
    "common/button_green.png",
    "common/button_gray.png",
    "common/colorframe_1.png",
    "material/8.png",
    "common/name_bg.png",
    "common/barrack_03.png",
    "common/frame_border_top.png",
    "common/bg_1.png",
    "common/bg_2.png",
    "common/bg_figure.png",
    "common/bg_3.png",
    "common/bg_4.png",
    "common/bg_5.png",
    "common/bg_6.png",
    "common/bg_7.png",
    "common/bg_8.png",
    "common/bg_9.png",
    "common/ui_hero_equitFrame.png",
    "item/20001.png",
    "common/button_green1.png",
    "common/gold_bg.png",
    "common/gold.png",
    "common/part_line.png",
    "common/bg_item.png",
    "item/21055.png",
    "common/title_bg1.png",
    "item/20751.png",
    "common/button_blue.png",
    "common/gold_bg.png",
    "common/gold.png",
    "common/build_icon.png",
    "common/button_green.png",
    "common/ui_barrack_sandTimer.png",
    "common/part_line.png",
    "common/special_bg.png",
    "common/bag_lock.png",
    "common/colorframe_1.png",
    "common/gem_cell.png",
    "equip/10001.png",
    "gem/101.png",
    "common/right1.png",
    "common/equip_bag_frame.png",
    "common/special_bg.png",
    "common/smith_forge_bg.png",
    "common/common_bg.png",
    "common/frame_border_top.png",
    "common/silver.png",
    "common/progress_bg.png",
    "common/ui_hero_progress.png",
    "common/ui_hero_progressHigh.png",
    "common/button_green1.png",
    "common/speedup.png",
    "common/cancel.png",
    "equip/10001.png",
    "common/color_table.png",
    "common/button_green.png",
    "common/forgeBook_icon.png",
    "common/colorframe_3.png",
    "material/5.png",
    "common/button_gray.png",
    "common/gold_bg.png",
    "common/gold.png",
    "common/colorframe_1.png",
    "material/8.png",
    "common/name_bg.png",
    "common/barrack_03.png",
    "common/frame_bg.png",
    "common/frame_bg_head.png",
    "common/button_back.png",
    "common/gold_frame.png",
    "common/add_gold.png",
    "common/frame_border_left.png",
    "common/frame_border_right.png",
    "common/frame_border_top.png",
    "common/frame_border_bottom.png",
    "common/frame_border_tl.png",
    "common/frame_border_tr.png",
    "common/frame_border_bl.png",
    "common/frame_border_br.png",
    "common/common_bg.png",
    "common/line_center.png",
    "common/line_left.png",
    "common/line_right.png",
    "common/desc_bg.png",
    "common/colorframe_2.png",
    "equip/10001.png",
    "gem/101.png",
    "common/barrack_03.png",
    "common/button_red.png",
    "common/chat_line.png",
    "common/button_green.png",
    "common/button_gray.png",
    "common/button_red.png",
    "common/line2_center.png",
    "common/line2_left.png",
    "common/line2_right.png",
    "common/colorframe_1.png",
    "common/kd_frame.png",
    "common/barrack_03.png",
    "gem/101.png",
    "common/desc_bg.png",
    "common/button_green.png",
    "common/production_bg.png",
    "common/heroxp.png",
    "common/frame_border_top.png",
    "common/button_green1.png",
    "common/mailPaper.png",
    "common/pen.png",
    "common/ui_barrack_soldierBack.png",
    "common/gold1.png",
    "common/text_bg.png",
    "common/wrong1.png",
    "common/button_green2.png",
    "common/tab_bg_checked.png",
    "common/mail_icon.png",
    "common/num_bg.png",
    "common/notice_icon.png",
    "common/collect_icon.png",
    "common/union_icon.png",
    "common/bg_1.png",
    "common/bg_2.png",
    "common/bg_3.png",
    "common/bg_4.png",
    "common/bg_5.png",
    "common/bg_6.png",
    "common/bg_7.png",
    "common/bg_8.png",
    "common/bg_9.png",
    "common/bg_figure.png",
    "common/checkBox.png",
    "common/right.png",
    "common/star_bg.png",
    "common/star.png",
    "common/button_green.png",
    "common/bg1_2.png",
    "common/bg1_1.png",
    "common/button_blue.png",
    "common/wrong.png",
    "common/bg_1.png",
    "common/bg_2.png",
    "common/bg_3.png",
    "common/bg_4.png",
    "common/bg_5.png",
    "common/bg_6.png",
    "common/bg_7.png",
    "common/bg_8.png",
    "common/bg_9.png",
    "common/bg_figure.png",
    "common/bg1_2.png",
    "common/bg1_1.png",
    "common/button_blue.png",
    "common/frame_border_top.png",
    "common/btn_gray1.png",
    "common/pageTurn.png",
    "common/star_bg.png",
    "common/star.png",
    "common/part_line.png",
    "common/bg_1.png",
    "common/bg_2.png",
    "common/bg_3.png",
    "common/bg_4.png",
    "common/bg_5.png",
    "common/bg_6.png",
    "common/bg_7.png",
    "common/bg_8.png",
    "common/bg_9.png",
    "common/header.png",
    "common/pen.png",
    "common/paper.png",
    "common/attachment.png",
    "common/button_green1.png",
    "common/frame_bg_head.png",
    "common/line_center.png",
    "common/line_left.png",
    "common/line_right.png",
    "common/frame_border_top.png",
    "common/btn_tab.png",
    "common/line2_center.png",
    "common/line2_left.png",
    "common/line2_right.png",
    "building/farm_1.png",
    "common/building_name_bg.png",
    "common/button_green1.png",
    "common/title3_bg.png",
    "common/attack_icon.png",
    "common/arrow_right.png",
    "common/food_big.png",
    "common/mine_big.png",
    "common/button_green.png",
    "common/main_bg_bottom.png",
    "common/frame_border_top.png",
    "common/chat_bg.png",
    "common/main_itemSelected_bg.png",
    "common/map_icon_bg.png",
    "common/city_icon.png",
    "common/quests.png",
    "common/num_bg.png",
    "common/items.png",
    "common/union.png",
    "common/mail.png",
    "common/more.png",
    "common/chat.png",
    "common/online.png",
    "common/msg.png",
    "common/special_bg.png",
    "common/line_center.png",
    "common/line_left.png",
    "common/line_right.png",
    "common/btn_tab.png",
    "common/gem_icon.png",
    "common/material_icon.png",
    "common/colorframe_1.png",
    "material/8.png",
    "common/name_bg.png",
    "common/barrack_03.png",
    "common/button_blue.png",
    "common/button_green.png",
    "common/desc_bg.png",
    "common/production_bg.png",
    "common/food_big.png",
    "common/btn_gray1.png",
    "common/help.png",
    "common/button_green.png",
    "common/head_bg.png",
    "research/110.png",
    "common/progress1_bg.png",
    "common/progress1.png",
    "common/button_blue.png",
    "common/gold_bg.png",
    "common/gold.png",
    "common/button_green.png",
    "common/title_desc_bg.png",
    "common/line2_center.png",
    "common/line2_left.png",
    "common/line2_right.png",
    "common/build_icon2.png",
    "common/wrong.png",
    "common/food_big.png",
    "common/right.png",
    "common/heroxp.png",
    "research/110.png",
    "common/button_blue.png",
    "common/button_green.png",
    "common/colorframe_1.png",
    "common/colorframe_5.png",
    "common/silver.png",
    "common/food.png",
    "common/wood.png",
    "common/rock.png",
    "common/mine.png",
    "common/bg_1.png",
    "common/bg_2.png",
    "common/bg_figure.png",
    "common/bg_3.png",
    "common/bg_4.png",
    "common/bg_5.png",
    "common/bg_6.png",
    "common/bg_7.png",
    "common/bg_8.png",
    "common/bg_9.png",
    "common/ui_hero_equitFrame.png",
    "item/20001.png",
    "common/button_green1.png",
    "common/gold_bg.png",
    "common/gold.png",
    "common/part_line.png",
    "common/bg_item.png",
    "item/21055.png",
    "common/frame_bg_head.png",
    "common/frame_border_top.png",
    "common/line_left.png",
    "common/line_right.png",
    "common/line_center.png",
    "common/ui_barrack_soldierBack.png",
    "common/gold1.png",
    "common/text_bg.png",
    "common/wrong1.png",
    "common/button_green2.png",
    "common/btn_tab.png",
    "common/btn_red2.png",
    "common/btn_red1.png",
    "common/desc_bg.png",
    "common/bg_1.png",
    "common/bg_2.png",
    "common/bg_figure.png",
    "common/bg_3.png",
    "common/bg_4.png",
    "common/bg_5.png",
    "common/bg_6.png",
    "common/bg_7.png",
    "common/bg_8.png",
    "common/bg_9.png",
    "common/ui_hero_equitFrame.png",
    "item/20001.png",
    "common/button_green1.png",
    "common/gold_bg.png",
    "common/gold.png",
    "common/part_line.png",
    "common/bg_item.png",
    "item/21055.png",
    "common/line2_center.png",
    "common/line2_left.png",
    "common/line2_right.png",
    "common/smith_make.png",
    "common/arrow_right.png",
    "common/smith_com.png",
    "common/smith_bag.png",
    "common/smith_material.png",
    "common/button_green.png",
    "common/progress_bg.png",
    "common/ui_hero_progress.png",
    "common/ui_hero_progressHigh.png",
    "common/bg_1.png",
    "common/bg_2.png",
    "common/bg_figure.png",
    "common/bg_3.png",
    "common/bg_4.png",
    "common/bg_5.png",
    "common/bg_6.png",
    "common/bg_7.png",
    "common/bg_8.png",
    "common/bg_9.png",
    "common/ui_hero_equitFrame.png",
    "item/20001.png",
    "common/button_green1.png",
    "common/gold_bg.png",
    "common/gold.png",
    "common/part_line.png",
    "common/bg_item.png",
    "item/21055.png",
    "common/desc_bg.png",
    "common/production_bg.png",
    "common/food_big.png",
    "common/wood_big.png",
    "common/mine_big.png",
    "common/rock_big.png",
    "common/button_green.png",
    "common/special_bg.png",
    "common/head_bg.png",
    "common/frame_border_top.png",
    "common/quest_5.png",
    "common/desc_bg.png",
    "common/line.png",
    "common/line1.png",
    "common/progress_bg.png",
    "common/progress.png",
    "common/progress_highlight.png",
    "common/progress_break.png",
    "common/progress_frame.png",
    "common/point_icon.png",
    "common/button_blue.png",
    "common/button_yellow.png",
    "common/vipicon_frame.png",
    "common/vip_icon_1.png",
    "common/lock1.png",
    "common/vip_icon_2.png",
    "common/vip_icon_3.png",
    "common/vip_icon_4.png",
    "common/vip_icon_5.png",
    "common/vip_icon_6.png",
    "common/vip_icon_7.png",
    "common/vip_icon_8.png",
    "common/vip_icon_9.png",
    "common/vip_icon_10.png",
    "common/vip_icon.png",
    "common/desc_bg.png",
    "common/page_point_off.png",
    "common/special_bg1.png",
    "common/line2.png",
    "common/vip_icon_1.png",
    "common/star.png",
    "common/button_blue.png",
    "common/button_yellow.png",
    "common/button_red.png",
    "common/button_green.png",
    "common/desc_bg.png",
    "common/button_green.png",
    "common/frame_bg_head.png",
    "common/line_center.png",
    "common/line_left.png",
    "common/line_right.png",
    "common/frame_border_top.png",
    "common/btn_tab.png",
    "common/line2_center.png",
    "common/line2_left.png",
    "common/line2_right.png",
    "heroHeadpic/02.png",
    "common/head_frame.png",
    "common/button_green.png",
    "common/button_red.png",
    "common/button_gray.png",
    "common/gold_bg.png",
    "common/ui_barrack_sandTimer.png",
    "common/alliance_17.png",
    "common/line_center.png",
    "common/line_left.png",
    "common/line_right.png",
    "common/progress_bg.png",
    "common/ui_hero_progress.png",
    "common/ui_hero_progressHigh.png",
    "common/quest_6.png",
    "common/research_icon.png",
    "common/desc_bg.png",
    "common/line2_center.png",
    "common/line2_left.png",
    "common/line2_right.png",
    "heroHeadpic/02.png",
    "common/head_frame.png",
    "common/alliance_17.png",
    "common/line_center.png",
    "common/line_left.png",
    "common/line_right.png",
    "common/button_green.png",
    "common/ui_barrack_frame1.png",
    "item/20503.png",
    "common/dlg_bg_yellow1.png",
    "common/dlg_lingL.png",
    "common/dlg_lingR.png",
    "common/dlg_lingB.png",
    "common/dlg_lineT.png",
    "common/dlg_lineTL.png",
    "common/dlg_lineTR.png",
    "common/dlg_lingBL.png",
    "common/dlg_lineBR.png",
    "common/guider_01.png",
    "common/button_green.png",
    "common/transparent.png",
    "common/guide_line.png",
    "common/guide_point.png",
    "common/guide_bg.png",
    "common/guide_blackBg.png",
    "common/dlg_bg_yellow1.png",
    "common/dlg_lingL.png",
    "common/dlg_lingR.png",
    "common/dlg_lingB.png",
    "common/dlg_lineT.png",
    "common/dlg_lineTL.png",
    "common/dlg_lineTR.png",
    "common/dlg_lingBL.png",
    "common/dlg_lineBR.png",
    "common/transparent.png",
    "common/guide_line.png",
    "common/guide_point.png"
  ],
  "version": "1.5.0.0",
  "widgetTree": {
    "classname": "Panel",
    "name": null,
    "children": [
      {
        "classname": "Panel",
        "name": null,
        "children": [
          {
            "classname": "ImageView",
            "name": null,
            "children": [
              {
                "classname": "ImageView",
                "name": null,
                "children": [],
                "options": {
                  "__type": "ImageViewSurrogate:#EditorCommon.JsonModel.Component.GUI",
                  "classname": "ImageView",
                  "name": "Image_1",
                  "ZOrder": 0,
                  "actiontag": 5,
                  "anchorPointX": 1,
                  "anchorPointY": 0.5,
                  "classType": "CocoStudio.EngineAdapterWrap.CSImageView",
                  "colorB": 255,
                  "colorG": 255,
                  "colorR": 255,
                  "customProperty": "",
                  "flipX": false,
                  "flipY": false,
                  "height": 960,
                  "ignoreSize": false,
                  "layoutParameter": null,
                  "opacity": 255,
                  "positionPercentX": -0.5,
                  "positionPercentY": 0,
                  "positionType": 0,
                  "rotation": 0,
                  "scaleX": 1,
                  "scaleY": 1,
                  "sizePercentX": 1,
                  "sizePercentY": 1,
                  "sizeType": 0,
                  "tag": 17177,
                  "touchAble": false,
                  "useMergedTexture": false,
                  "visible": true,
                  "width": 640,
                  "x": -320,
                  "y": 0,
                  "capInsetsHeight": 1,
                  "capInsetsWidth": 1,
                  "capInsetsX": 0,
                  "capInsetsY": 0,
                  "fileName": null,
                  "fileNameData": {
                    "path": "common/guide_blackBg.png",
                    "plistFile": "",
                    "resourceType": 0
                  },
                  "scale9Enable": false,
                  "scale9Height": 960,
                  "scale9Width": 640
                }
              },
              {
                "classname": "ImageView",
                "name": null,
                "children": [],
                "options": {
                  "__type": "ImageViewSurrogate:#EditorCommon.JsonModel.Component.GUI",
                  "classname": "ImageView",
                  "name": "Image_2",
                  "ZOrder": 0,
                  "actiontag": 13,
                  "anchorPointX": 0,
                  "anchorPointY": 0.5,
                  "classType": "CocoStudio.EngineAdapterWrap.CSImageView",
                  "colorB": 255,
                  "colorG": 255,
                  "colorR": 255,
                  "customProperty": "",
                  "flipX": false,
                  "flipY": false,
                  "height": 960,
                  "ignoreSize": false,
                  "layoutParameter": null,
                  "opacity": 255,
                  "positionPercentX": 0.5,
                  "positionPercentY": 0,
                  "positionType": 0,
                  "rotation": 0,
                  "scaleX": 1,
                  "scaleY": 1,
                  "sizePercentX": 1,
                  "sizePercentY": 1,
                  "sizeType": 0,
                  "tag": 17184,
                  "touchAble": false,
                  "useMergedTexture": false,
                  "visible": true,
                  "width": 640,
                  "x": 320,
                  "y": 0,
                  "capInsetsHeight": 1,
                  "capInsetsWidth": 1,
                  "capInsetsX": 0,
                  "capInsetsY": 0,
                  "fileName": null,
                  "fileNameData": {
                    "path": "common/guide_blackBg.png",
                    "plistFile": "",
                    "resourceType": 0
                  },
                  "scale9Enable": false,
                  "scale9Height": 960,
                  "scale9Width": 640
                }
              },
              {
                "classname": "ImageView",
                "name": null,
                "children": [],
                "options": {
                  "__type": "ImageViewSurrogate:#EditorCommon.JsonModel.Component.GUI",
                  "classname": "ImageView",
                  "name": "Image_3",
                  "ZOrder": 0,
                  "actiontag": 15,
                  "anchorPointX": 0.5,
                  "anchorPointY": 0,
                  "classType": "CocoStudio.EngineAdapterWrap.CSImageView",
                  "colorB": 255,
                  "colorG": 255,
                  "colorR": 255,
                  "customProperty": "",
                  "flipX": false,
                  "flipY": false,
                  "height": 960,
                  "ignoreSize": false,
                  "layoutParameter": null,
                  "opacity": 255,
                  "positionPercentX": 0,
                  "positionPercentY": 0.5,
                  "positionType": 0,
                  "rotation": 0,
                  "scaleX": 1,
                  "scaleY": 1,
                  "sizePercentX": 1,
                  "sizePercentY": 1,
                  "sizeType": 0,
                  "tag": 17186,
                  "touchAble": false,
                  "useMergedTexture": false,
                  "visible": true,
                  "width": 640,
                  "x": 0,
                  "y": 480,
                  "capInsetsHeight": 1,
                  "capInsetsWidth": 1,
                  "capInsetsX": 0,
                  "capInsetsY": 0,
                  "fileName": null,
                  "fileNameData": {
                    "path": "common/guide_blackBg.png",
                    "plistFile": "",
                    "resourceType": 0
                  },
                  "scale9Enable": false,
                  "scale9Height": 960,
                  "scale9Width": 640
                }
              },
              {
                "classname": "ImageView",
                "name": null,
                "children": [],
                "options": {
                  "__type": "ImageViewSurrogate:#EditorCommon.JsonModel.Component.GUI",
                  "classname": "ImageView",
                  "name": "Image_3_2",
                  "ZOrder": 0,
                  "actiontag": 18,
                  "anchorPointX": 0,
                  "anchorPointY": 0,
                  "classType": "CocoStudio.EngineAdapterWrap.CSImageView",
                  "colorB": 255,
                  "colorG": 255,
                  "colorR": 255,
                  "customProperty": "",
                  "flipX": false,
                  "flipY": false,
                  "height": 960,
                  "ignoreSize": false,
                  "layoutParameter": null,
                  "opacity": 255,
                  "positionPercentX": 0.5,
                  "positionPercentY": 0.5,
                  "positionType": 0,
                  "rotation": 0,
                  "scaleX": 1,
                  "scaleY": 1,
                  "sizePercentX": 1,
                  "sizePercentY": 1,
                  "sizeType": 0,
                  "tag": 17188,
                  "touchAble": false,
                  "useMergedTexture": false,
                  "visible": true,
                  "width": 640,
                  "x": 320,
                  "y": 480,
                  "capInsetsHeight": 1,
                  "capInsetsWidth": 1,
                  "capInsetsX": 0,
                  "capInsetsY": 0,
                  "fileName": null,
                  "fileNameData": {
                    "path": "common/guide_blackBg.png",
                    "plistFile": "",
                    "resourceType": 0
                  },
                  "scale9Enable": false,
                  "scale9Height": 960,
                  "scale9Width": 640
                }
              },
              {
                "classname": "ImageView",
                "name": null,
                "children": [],
                "options": {
                  "__type": "ImageViewSurrogate:#EditorCommon.JsonModel.Component.GUI",
                  "classname": "ImageView",
                  "name": "Image_3_1",
                  "ZOrder": 0,
                  "actiontag": 21,
                  "anchorPointX": 1,
                  "anchorPointY": 0,
                  "classType": "CocoStudio.EngineAdapterWrap.CSImageView",
                  "colorB": 255,
                  "colorG": 255,
                  "colorR": 255,
                  "customProperty": "",
                  "flipX": false,
                  "flipY": false,
                  "height": 960,
                  "ignoreSize": false,
                  "layoutParameter": null,
                  "opacity": 255,
                  "positionPercentX": -0.5,
                  "positionPercentY": 0.5,
                  "positionType": 0,
                  "rotation": 0,
                  "scaleX": 1,
                  "scaleY": 1,
                  "sizePercentX": 1,
                  "sizePercentY": 1,
                  "sizeType": 0,
                  "tag": 17189,
                  "touchAble": false,
                  "useMergedTexture": false,
                  "visible": true,
                  "width": 640,
                  "x": -320,
                  "y": 480,
                  "capInsetsHeight": 1,
                  "capInsetsWidth": 1,
                  "capInsetsX": 0,
                  "capInsetsY": 0,
                  "fileName": null,
                  "fileNameData": {
                    "path": "common/guide_blackBg.png",
                    "plistFile": "",
                    "resourceType": 0
                  },
                  "scale9Enable": false,
                  "scale9Height": 960,
                  "scale9Width": 640
                }
              },
              {
                "classname": "ImageView",
                "name": null,
                "children": [],
                "options": {
                  "__type": "ImageViewSurrogate:#EditorCommon.JsonModel.Component.GUI",
                  "classname": "ImageView",
                  "name": "Image_4",
                  "ZOrder": 0,
                  "actiontag": 22,
                  "anchorPointX": 0.5,
                  "anchorPointY": 1,
                  "classType": "CocoStudio.EngineAdapterWrap.CSImageView",
                  "colorB": 255,
                  "colorG": 255,
                  "colorR": 255,
                  "customProperty": "",
                  "flipX": false,
                  "flipY": false,
                  "height": 960,
                  "ignoreSize": false,
                  "layoutParameter": null,
                  "opacity": 255,
                  "positionPercentX": 0,
                  "positionPercentY": -0.5,
                  "positionType": 0,
                  "rotation": 0,
                  "scaleX": 1,
                  "scaleY": 1,
                  "sizePercentX": 1,
                  "sizePercentY": 1,
                  "sizeType": 0,
                  "tag": 17190,
                  "touchAble": false,
                  "useMergedTexture": false,
                  "visible": true,
                  "width": 640,
                  "x": 0,
                  "y": -480,
                  "capInsetsHeight": 1,
                  "capInsetsWidth": 1,
                  "capInsetsX": 0,
                  "capInsetsY": 0,
                  "fileName": null,
                  "fileNameData": {
                    "path": "common/guide_blackBg.png",
                    "plistFile": "",
                    "resourceType": 0
                  },
                  "scale9Enable": false,
                  "scale9Height": 960,
                  "scale9Width": 640
                }
              },
              {
                "classname": "ImageView",
                "name": null,
                "children": [],
                "options": {
                  "__type": "ImageViewSurrogate:#EditorCommon.JsonModel.Component.GUI",
                  "classname": "ImageView",
                  "name": "Image_4_1",
                  "ZOrder": 0,
                  "actiontag": 24,
                  "anchorPointX": 0,
                  "anchorPointY": 1,
                  "classType": "CocoStudio.EngineAdapterWrap.CSImageView",
                  "colorB": 255,
                  "colorG": 255,
                  "colorR": 255,
                  "customProperty": "",
                  "flipX": false,
                  "flipY": false,
                  "height": 960,
                  "ignoreSize": false,
                  "layoutParameter": null,
                  "opacity": 255,
                  "positionPercentX": 0.5,
                  "positionPercentY": -0.5,
                  "positionType": 0,
                  "rotation": 0,
                  "scaleX": 1,
                  "scaleY": 1,
                  "sizePercentX": 1,
                  "sizePercentY": 1,
                  "sizeType": 0,
                  "tag": 17192,
                  "touchAble": false,
                  "useMergedTexture": false,
                  "visible": true,
                  "width": 640,
                  "x": 320,
                  "y": -480,
                  "capInsetsHeight": 1,
                  "capInsetsWidth": 1,
                  "capInsetsX": 0,
                  "capInsetsY": 0,
                  "fileName": null,
                  "fileNameData": {
                    "path": "common/guide_blackBg.png",
                    "plistFile": "",
                    "resourceType": 0
                  },
                  "scale9Enable": false,
                  "scale9Height": 960,
                  "scale9Width": 640
                }
              },
              {
                "classname": "ImageView",
                "name": null,
                "children": [],
                "options": {
                  "__type": "ImageViewSurrogate:#EditorCommon.JsonModel.Component.GUI",
                  "classname": "ImageView",
                  "name": "Image_4_2",
                  "ZOrder": 0,
                  "actiontag": 26,
                  "anchorPointX": 1,
                  "anchorPointY": 1,
                  "classType": "CocoStudio.EngineAdapterWrap.CSImageView",
                  "colorB": 255,
                  "colorG": 255,
                  "colorR": 255,
                  "customProperty": "",
                  "flipX": false,
                  "flipY": false,
                  "height": 960,
                  "ignoreSize": false,
                  "layoutParameter": null,
                  "opacity": 255,
                  "positionPercentX": -0.5,
                  "positionPercentY": -0.5,
                  "positionType": 0,
                  "rotation": 0,
                  "scaleX": 1,
                  "scaleY": 1,
                  "sizePercentX": 1,
                  "sizePercentY": 1,
                  "sizeType": 0,
                  "tag": 17193,
                  "touchAble": false,
                  "useMergedTexture": false,
                  "visible": true,
                  "width": 640,
                  "x": -320,
                  "y": -480,
                  "capInsetsHeight": 1,
                  "capInsetsWidth": 1,
                  "capInsetsX": 0,
                  "capInsetsY": 0,
                  "fileName": null,
                  "fileNameData": {
                    "path": "common/guide_blackBg.png",
                    "plistFile": "",
                    "resourceType": 0
                  },
                  "scale9Enable": false,
                  "scale9Height": 960,
                  "scale9Width": 640
                }
              }
            ],
            "options": {
              "__type": "ImageViewSurrogate:#EditorCommon.JsonModel.Component.GUI",
              "classname": "ImageView",
              "name": "Image_bg",
              "ZOrder": 0,
              "actiontag": 3,
              "anchorPointX": 0.5,
              "anchorPointY": 0.5,
              "classType": "CocoStudio.EngineAdapterWrap.CSImageView",
              "colorB": 255,
              "colorG": 255,
              "colorR": 255,
              "customProperty": "",
              "flipX": false,
              "flipY": false,
              "height": 960,
              "ignoreSize": true,
              "layoutParameter": null,
              "opacity": 255,
              "positionPercentX": 0.5,
              "positionPercentY": 0.5,
              "positionType": 0,
              "rotation": 0,
              "scaleX": 1,
              "scaleY": 1,
              "sizePercentX": 1,
              "sizePercentY": 1,
              "sizeType": 0,
              "tag": 17132,
              "touchAble": false,
              "useMergedTexture": false,
              "visible": true,
              "width": 640,
              "x": 320,
              "y": 480,
              "capInsetsHeight": 10,
              "capInsetsWidth": 10,
              "capInsetsX": 0,
              "capInsetsY": 0,
              "fileName": null,
              "fileNameData": {
                "path": "common/guide_bg.png",
                "plistFile": "",
                "resourceType": 0
              },
              "scale9Enable": false,
              "scale9Height": 960,
              "scale9Width": 640
            }
          }
        ],
        "options": {
          "__type": "PanelSurrogate:#EditorCommon.JsonModel.Component.GUI",
          "classname": "Panel",
          "name": "Panel_frame",
          "ZOrder": 0,
          "actiontag": 2,
          "anchorPointX": 0,
          "anchorPointY": 0,
          "classType": "CocoStudio.EngineAdapterWrap.CSPanel",
          "colorB": 255,
          "colorG": 255,
          "colorR": 255,
          "customProperty": "",
          "flipX": false,
          "flipY": false,
          "height": 960,
          "ignoreSize": false,
          "layoutParameter": null,
          "opacity": 255,
          "positionPercentX": 0,
          "positionPercentY": 0,
          "positionType": 0,
          "rotation": 0,
          "scaleX": 1,
          "scaleY": 1,
          "sizePercentX": 1,
          "sizePercentY": 1,
          "sizeType": 0,
          "tag": -99,
          "touchAble": false,
          "useMergedTexture": false,
          "visible": true,
          "width": 640,
          "x": 0,
          "y": 0,
          "adaptScreen": false,
          "backGroundImage": null,
          "backGroundImageData": null,
          "backGroundScale9Enable": false,
          "bgColorB": 255,
          "bgColorG": 200,
          "bgColorOpacity": 100,
          "bgColorR": 150,
          "bgEndColorB": 255,
          "bgEndColorG": 200,
          "bgEndColorR": 150,
          "bgStartColorB": 255,
          "bgStartColorG": 255,
          "bgStartColorR": 255,
          "capInsetsHeight": 1,
          "capInsetsWidth": 1,
          "capInsetsX": 0,
          "capInsetsY": 0,
          "clipAble": false,
          "colorType": 0,
          "layoutType": 0,
          "vectorX": 0,
          "vectorY": -0.5
        }
      },
      {
        "classname": "Panel",
        "name": null,
        "children": [
          {
            "classname": "ImageView",
            "name": null,
            "children": [],
            "options": {
              "__type": "ImageViewSurrogate:#EditorCommon.JsonModel.Component.GUI",
              "classname": "ImageView",
              "name": "Image_bg",
              "ZOrder": 0,
              "actiontag": 40,
              "anchorPointX": 0,
              "anchorPointY": 0,
              "classType": "CocoStudio.EngineAdapterWrap.CSImageView",
              "colorB": 255,
              "colorG": 255,
              "colorR": 255,
              "customProperty": "",
              "flipX": false,
              "flipY": false,
              "height": 120,
              "ignoreSize": false,
              "layoutParameter": null,
              "opacity": 255,
              "positionPercentX": 0.025,
              "positionPercentY": 0,
              "positionType": 0,
              "rotation": 0,
              "scaleX": 1,
              "scaleY": 1,
              "sizePercentX": 0.953125,
              "sizePercentY": 0.9230769,
              "sizeType": 0,
              "tag": 23014,
              "touchAble": false,
              "useMergedTexture": false,
              "visible": true,
              "width": 610,
              "x": 16,
              "y": 0,
              "capInsetsHeight": 1,
              "capInsetsWidth": 1,
              "capInsetsX": 0,
              "capInsetsY": 0,
              "fileName": null,
              "fileNameData": {
                "path": "common/dlg_bg_yellow1.png",
                "plistFile": "",
                "resourceType": 0
              },
              "scale9Enable": false,
              "scale9Height": 120,
              "scale9Width": 610
            }
          },
          {
            "classname": "ImageView",
            "name": null,
            "children": [],
            "options": {
              "__type": "ImageViewSurrogate:#EditorCommon.JsonModel.Component.GUI",
              "classname": "ImageView",
              "name": "Image_v1",
              "ZOrder": 0,
              "actiontag": 41,
              "anchorPointX": 0,
              "anchorPointY": 0,
              "classType": "CocoStudio.EngineAdapterWrap.CSImageView",
              "colorB": 255,
              "colorG": 255,
              "colorR": 255,
              "customProperty": "",
              "flipX": false,
              "flipY": false,
              "height": 120,
              "ignoreSize": false,
              "layoutParameter": null,
              "opacity": 255,
              "positionPercentX": 0.015625,
              "positionPercentY": 0,
              "positionType": 0,
              "rotation": 0,
              "scaleX": 1,
              "scaleY": 1,
              "sizePercentX": 0.0375,
              "sizePercentY": 0.9230769,
              "sizeType": 0,
              "tag": -92,
              "touchAble": false,
              "useMergedTexture": false,
              "visible": true,
              "width": 24,
              "x": 10,
              "y": 0,
              "capInsetsHeight": 1,
              "capInsetsWidth": 1,
              "capInsetsX": 0,
              "capInsetsY": 0,
              "fileName": null,
              "fileNameData": {
                "path": "common/dlg_lingL.png",
                "plistFile": "",
                "resourceType": 0
              },
              "scale9Enable": false,
              "scale9Height": 120,
              "scale9Width": 24
            }
          },
          {
            "classname": "ImageView",
            "name": null,
            "children": [],
            "options": {
              "__type": "ImageViewSurrogate:#EditorCommon.JsonModel.Component.GUI",
              "classname": "ImageView",
              "name": "Image_v2",
              "ZOrder": 0,
              "actiontag": 42,
              "anchorPointX": 0.8,
              "anchorPointY": 0,
              "classType": "CocoStudio.EngineAdapterWrap.CSImageView",
              "colorB": 255,
              "colorG": 255,
              "colorR": 255,
              "customProperty": "",
              "flipX": false,
              "flipY": false,
              "height": 120,
              "ignoreSize": false,
              "layoutParameter": null,
              "opacity": 255,
              "positionPercentX": 0.98125,
              "positionPercentY": -0.0153846154,
              "positionType": 0,
              "rotation": 0,
              "scaleX": 1,
              "scaleY": 1,
              "sizePercentX": 0.0375,
              "sizePercentY": 0.9230769,
              "sizeType": 0,
              "tag": -92,
              "touchAble": false,
              "useMergedTexture": false,
              "visible": true,
              "width": 24,
              "x": 628,
              "y": -2,
              "capInsetsHeight": 1,
              "capInsetsWidth": 1,
              "capInsetsX": 0,
              "capInsetsY": 0,
              "fileName": null,
              "fileNameData": {
                "path": "common/dlg_lingR.png",
                "plistFile": "",
                "resourceType": 0
              },
              "scale9Enable": false,
              "scale9Height": 120,
              "scale9Width": 24
            }
          },
          {
            "classname": "ImageView",
            "name": null,
            "children": [],
            "options": {
              "__type": "ImageViewSurrogate:#EditorCommon.JsonModel.Component.GUI",
              "classname": "ImageView",
              "name": "Image_h1",
              "ZOrder": 0,
              "actiontag": 43,
              "anchorPointX": 0,
              "anchorPointY": 0,
              "classType": "CocoStudio.EngineAdapterWrap.CSImageView",
              "colorB": 255,
              "colorG": 255,
              "colorR": 255,
              "customProperty": "",
              "flipX": false,
              "flipY": false,
              "height": 24,
              "ignoreSize": false,
              "layoutParameter": null,
              "opacity": 255,
              "positionPercentX": 0.01875,
              "positionPercentY": -0.0461538471,
              "positionType": 0,
              "rotation": 0,
              "scaleX": 1,
              "scaleY": 1,
              "sizePercentX": 0.959375,
              "sizePercentY": 0.184615389,
              "sizeType": 0,
              "tag": -91,
              "touchAble": false,
              "useMergedTexture": false,
              "visible": true,
              "width": 614,
              "x": 12,
              "y": -6,
              "capInsetsHeight": 1,
              "capInsetsWidth": 1,
              "capInsetsX": 0,
              "capInsetsY": 0,
              "fileName": null,
              "fileNameData": {
                "path": "common/dlg_lingB.png",
                "plistFile": "",
                "resourceType": 0
              },
              "scale9Enable": false,
              "scale9Height": 24,
              "scale9Width": 614
            }
          },
          {
            "classname": "ImageView",
            "name": null,
            "children": [],
            "options": {
              "__type": "ImageViewSurrogate:#EditorCommon.JsonModel.Component.GUI",
              "classname": "ImageView",
              "name": "Image_h2",
              "ZOrder": 0,
              "actiontag": 44,
              "anchorPointX": 0,
              "anchorPointY": 1,
              "classType": "CocoStudio.EngineAdapterWrap.CSImageView",
              "colorB": 255,
              "colorG": 255,
              "colorR": 255,
              "customProperty": "",
              "flipX": false,
              "flipY": false,
              "height": 24,
              "ignoreSize": false,
              "layoutParameter": null,
              "opacity": 255,
              "positionPercentX": 0.01875,
              "positionPercentY": 0.938461542,
              "positionType": 0,
              "rotation": 0,
              "scaleX": 1,
              "scaleY": 1,
              "sizePercentX": 0.95625,
              "sizePercentY": 0.184615389,
              "sizeType": 0,
              "tag": -91,
              "touchAble": false,
              "useMergedTexture": false,
              "visible": true,
              "width": 612,
              "x": 12,
              "y": 122,
              "capInsetsHeight": 1,
              "capInsetsWidth": 1,
              "capInsetsX": 0,
              "capInsetsY": 0,
              "fileName": null,
              "fileNameData": {
                "path": "common/dlg_lineT.png",
                "plistFile": "",
                "resourceType": 0
              },
              "scale9Enable": false,
              "scale9Height": 24,
              "scale9Width": 612
            }
          },
          {
            "classname": "ImageView",
            "name": null,
            "children": [],
            "options": {
              "__type": "ImageViewSurrogate:#EditorCommon.JsonModel.Component.GUI",
              "classname": "ImageView",
              "name": "Image_1",
              "ZOrder": 0,
              "actiontag": 45,
              "anchorPointX": 0,
              "anchorPointY": 1,
              "classType": "CocoStudio.EngineAdapterWrap.CSImageView",
              "colorB": 255,
              "colorG": 255,
              "colorR": 255,
              "customProperty": "",
              "flipX": false,
              "flipY": false,
              "height": 24,
              "ignoreSize": true,
              "layoutParameter": null,
              "opacity": 255,
              "positionPercentX": 0.015625,
              "positionPercentY": 0.938461542,
              "positionType": 0,
              "rotation": 0,
              "scaleX": 1,
              "scaleY": 1,
              "sizePercentX": 0.0375,
              "sizePercentY": 0.184615389,
              "sizeType": 0,
              "tag": -93,
              "touchAble": false,
              "useMergedTexture": false,
              "visible": true,
              "width": 24,
              "x": 10,
              "y": 122,
              "capInsetsHeight": 1,
              "capInsetsWidth": 1,
              "capInsetsX": 0,
              "capInsetsY": 0,
              "fileName": null,
              "fileNameData": {
                "path": "common/dlg_lineTL.png",
                "plistFile": "",
                "resourceType": 0
              },
              "scale9Enable": false,
              "scale9Height": 24,
              "scale9Width": 24
            }
          },
          {
            "classname": "ImageView",
            "name": null,
            "children": [],
            "options": {
              "__type": "ImageViewSurrogate:#EditorCommon.JsonModel.Component.GUI",
              "classname": "ImageView",
              "name": "Image_2",
              "ZOrder": 0,
              "actiontag": 46,
              "anchorPointX": 0.8,
              "anchorPointY": 1,
              "classType": "CocoStudio.EngineAdapterWrap.CSImageView",
              "colorB": 255,
              "colorG": 255,
              "colorR": 255,
              "customProperty": "",
              "flipX": false,
              "flipY": false,
              "height": 24,
              "ignoreSize": true,
              "layoutParameter": null,
              "opacity": 255,
              "positionPercentX": 0.98125,
              "positionPercentY": 0.938461542,
              "positionType": 0,
              "rotation": 0,
              "scaleX": 1,
              "scaleY": 1,
              "sizePercentX": 0.0375,
              "sizePercentY": 0.184615389,
              "sizeType": 0,
              "tag": -93,
              "touchAble": false,
              "useMergedTexture": false,
              "visible": true,
              "width": 24,
              "x": 628,
              "y": 122,
              "capInsetsHeight": 1,
              "capInsetsWidth": 1,
              "capInsetsX": 0,
              "capInsetsY": 0,
              "fileName": null,
              "fileNameData": {
                "path": "common/dlg_lineTR.png",
                "plistFile": "",
                "resourceType": 0
              },
              "scale9Enable": false,
              "scale9Height": 24,
              "scale9Width": 24
            }
          },
          {
            "classname": "ImageView",
            "name": null,
            "children": [],
            "options": {
              "__type": "ImageViewSurrogate:#EditorCommon.JsonModel.Component.GUI",
              "classname": "ImageView",
              "name": "Image_3",
              "ZOrder": 0,
              "actiontag": 47,
              "anchorPointX": 0,
              "anchorPointY": 0,
              "classType": "CocoStudio.EngineAdapterWrap.CSImageView",
              "colorB": 255,
              "colorG": 255,
              "colorR": 255,
              "customProperty": "",
              "flipX": false,
              "flipY": false,
              "height": 24,
              "ignoreSize": true,
              "layoutParameter": null,
              "opacity": 255,
              "positionPercentX": 0.015625,
              "positionPercentY": -0.0538461544,
              "positionType": 0,
              "rotation": 0,
              "scaleX": 1,
              "scaleY": 1,
              "sizePercentX": 0.0375,
              "sizePercentY": 0.184615389,
              "sizeType": 0,
              "tag": -93,
              "touchAble": false,
              "useMergedTexture": false,
              "visible": true,
              "width": 24,
              "x": 10,
              "y": -7,
              "capInsetsHeight": 1,
              "capInsetsWidth": 1,
              "capInsetsX": 0,
              "capInsetsY": 0,
              "fileName": null,
              "fileNameData": {
                "path": "common/dlg_lingBL.png",
                "plistFile": "",
                "resourceType": 0
              },
              "scale9Enable": false,
              "scale9Height": 24,
              "scale9Width": 24
            }
          },
          {
            "classname": "ImageView",
            "name": null,
            "children": [],
            "options": {
              "__type": "ImageViewSurrogate:#EditorCommon.JsonModel.Component.GUI",
              "classname": "ImageView",
              "name": "Image_4",
              "ZOrder": 0,
              "actiontag": 48,
              "anchorPointX": 0.8,
              "anchorPointY": 0,
              "classType": "CocoStudio.EngineAdapterWrap.CSImageView",
              "colorB": 255,
              "colorG": 255,
              "colorR": 255,
              "customProperty": "",
              "flipX": false,
              "flipY": false,
              "height": 24,
              "ignoreSize": true,
              "layoutParameter": null,
              "opacity": 255,
              "positionPercentX": 0.98125,
              "positionPercentY": -0.0461538471,
              "positionType": 0,
              "rotation": 0,
              "scaleX": 1,
              "scaleY": 1,
              "sizePercentX": 0.0375,
              "sizePercentY": 0.184615389,
              "sizeType": 0,
              "tag": -93,
              "touchAble": false,
              "useMergedTexture": false,
              "visible": true,
              "width": 24,
              "x": 628,
              "y": -6,
              "capInsetsHeight": 1,
              "capInsetsWidth": 1,
              "capInsetsX": 0,
              "capInsetsY": 0,
              "fileName": null,
              "fileNameData": {
                "path": "common/dlg_lineBR.png",
                "plistFile": "",
                "resourceType": 0
              },
              "scale9Enable": false,
              "scale9Height": 24,
              "scale9Width": 24
            }
          }
        ],
        "options": {
          "__type": "PanelSurrogate:#EditorCommon.JsonModel.Component.GUI",
          "classname": "Panel",
          "name": "Panel_textBg",
          "ZOrder": 0,
          "actiontag": 39,
          "anchorPointX": 0,
          "anchorPointY": 0,
          "classType": "CocoStudio.EngineAdapterWrap.CSPanel",
          "colorB": 255,
          "colorG": 255,
          "colorR": 255,
          "customProperty": "",
          "flipX": false,
          "flipY": false,
          "height": 130,
          "ignoreSize": false,
          "layoutParameter": null,
          "opacity": 255,
          "positionPercentX": 0,
          "positionPercentY": 0.354166657,
          "positionType": 0,
          "rotation": 0,
          "scaleX": 1,
          "scaleY": 1,
          "sizePercentX": 1,
          "sizePercentY": 0.135416672,
          "sizeType": 0,
          "tag": -99,
          "touchAble": false,
          "useMergedTexture": false,
          "visible": false,
          "width": 640,
          "x": 0,
          "y": 340,
          "adaptScreen": false,
          "backGroundImage": null,
          "backGroundImageData": null,
          "backGroundScale9Enable": false,
          "bgColorB": 255,
          "bgColorG": 200,
          "bgColorOpacity": 100,
          "bgColorR": 150,
          "bgEndColorB": 255,
          "bgEndColorG": 200,
          "bgEndColorR": 150,
          "bgStartColorB": 255,
          "bgStartColorG": 255,
          "bgStartColorR": 255,
          "capInsetsHeight": 1,
          "capInsetsWidth": 1,
          "capInsetsX": 0,
          "capInsetsY": 0,
          "clipAble": false,
          "colorType": 0,
          "layoutType": 0,
          "vectorX": 0,
          "vectorY": -0.5
        }
      },
      {
        "classname": "Panel",
        "name": null,
        "children": [
          {
            "classname": "ImageView",
            "name": null,
            "children": [
              {
                "classname": "ImageView",
                "name": null,
                "children": [],
                "options": {
                  "__type": "ImageViewSurrogate:#EditorCommon.JsonModel.Component.GUI",
                  "classname": "ImageView",
                  "name": "Image_left",
                  "ZOrder": 0,
                  "actiontag": 19,
                  "anchorPointX": 1,
                  "anchorPointY": 0.5,
                  "classType": "CocoStudio.EngineAdapterWrap.CSImageView",
                  "colorB": 255,
                  "colorG": 255,
                  "colorR": 255,
                  "customProperty": "",
                  "flipX": false,
                  "flipY": false,
                  "height": 80,
                  "ignoreSize": false,
                  "layoutParameter": null,
                  "opacity": 255,
                  "positionPercentX": -0.797619045,
                  "positionPercentY": 0,
                  "positionType": 0,
                  "rotation": 0,
                  "scaleX": 1,
                  "scaleY": 1,
                  "sizePercentX": 0.0833333358,
                  "sizePercentY": 0.476190478,
                  "sizeType": 0,
                  "tag": 17148,
                  "touchAble": false,
                  "useMergedTexture": false,
                  "visible": true,
                  "width": 14,
                  "x": -134,
                  "y": 0,
                  "capInsetsHeight": 1,
                  "capInsetsWidth": 1,
                  "capInsetsX": 0,
                  "capInsetsY": 0,
                  "fileName": null,
                  "fileNameData": {
                    "path": "common/guide_line.png",
                    "plistFile": "",
                    "resourceType": 0
                  },
                  "scale9Enable": false,
                  "scale9Height": 80,
                  "scale9Width": 14
                }
              },
              {
                "classname": "ImageView",
                "name": null,
                "children": [],
                "options": {
                  "__type": "ImageViewSurrogate:#EditorCommon.JsonModel.Component.GUI",
                  "classname": "ImageView",
                  "name": "Image_top",
                  "ZOrder": 0,
                  "actiontag": 16,
                  "anchorPointX": 1,
                  "anchorPointY": 0.5,
                  "classType": "CocoStudio.EngineAdapterWrap.CSImageView",
                  "colorB": 255,
                  "colorG": 255,
                  "colorR": 255,
                  "customProperty": "",
                  "flipX": false,
                  "flipY": false,
                  "height": 284,
                  "ignoreSize": false,
                  "layoutParameter": null,
                  "opacity": 255,
                  "positionPercentX": 0,
                  "positionPercentY": 0.1904762,
                  "positionType": 0,
                  "rotation": 90,
                  "scaleX": 1,
                  "scaleY": 1,
                  "sizePercentX": 0.0833333358,
                  "sizePercentY": 1.69047618,
                  "sizeType": 0,
                  "tag": 17145,
                  "touchAble": false,
                  "useMergedTexture": false,
                  "visible": true,
                  "width": 14,
                  "x": 0,
                  "y": 32,
                  "capInsetsHeight": 1,
                  "capInsetsWidth": 1,
                  "capInsetsX": 0,
                  "capInsetsY": 0,
                  "fileName": null,
                  "fileNameData": {
                    "path": "common/guide_line.png",
                    "plistFile": "",
                    "resourceType": 0
                  },
                  "scale9Enable": false,
                  "scale9Height": 284,
                  "scale9Width": 14
                }
              },
              {
                "classname": "ImageView",
                "name": null,
                "children": [],
                "options": {
                  "__type": "ImageViewSurrogate:#EditorCommon.JsonModel.Component.GUI",
                  "classname": "ImageView",
                  "name": "Image_right",
                  "ZOrder": 0,
                  "actiontag": 20,
                  "anchorPointX": 0,
                  "anchorPointY": 0.5,
                  "classType": "CocoStudio.EngineAdapterWrap.CSImageView",
                  "colorB": 255,
                  "colorG": 255,
                  "colorR": 255,
                  "customProperty": "",
                  "flipX": true,
                  "flipY": false,
                  "height": 80,
                  "ignoreSize": false,
                  "layoutParameter": null,
                  "opacity": 255,
                  "positionPercentX": 0.797619045,
                  "positionPercentY": 0,
                  "positionType": 0,
                  "rotation": 0,
                  "scaleX": 1,
                  "scaleY": 1,
                  "sizePercentX": 0.0833333358,
                  "sizePercentY": 0.476190478,
                  "sizeType": 0,
                  "tag": 17149,
                  "touchAble": false,
                  "useMergedTexture": false,
                  "visible": true,
                  "width": 14,
                  "x": 134,
                  "y": 0,
                  "capInsetsHeight": 1,
                  "capInsetsWidth": 1,
                  "capInsetsX": 0,
                  "capInsetsY": 0,
                  "fileName": null,
                  "fileNameData": {
                    "path": "common/guide_line.png",
                    "plistFile": "",
                    "resourceType": 0
                  },
                  "scale9Enable": false,
                  "scale9Height": 80,
                  "scale9Width": 14
                }
              },
              {
                "classname": "ImageView",
                "name": null,
                "children": [],
                "options": {
                  "__type": "ImageViewSurrogate:#EditorCommon.JsonModel.Component.GUI",
                  "classname": "ImageView",
                  "name": "Image_bottom",
                  "ZOrder": 0,
                  "actiontag": 25,
                  "anchorPointX": 0,
                  "anchorPointY": 0.5,
                  "classType": "CocoStudio.EngineAdapterWrap.CSImageView",
                  "colorB": 255,
                  "colorG": 255,
                  "colorR": 255,
                  "customProperty": "",
                  "flipX": true,
                  "flipY": false,
                  "height": 284,
                  "ignoreSize": false,
                  "layoutParameter": null,
                  "opacity": 255,
                  "positionPercentX": 0,
                  "positionPercentY": -0.1904762,
                  "positionType": 0,
                  "rotation": 90,
                  "scaleX": 1,
                  "scaleY": 1,
                  "sizePercentX": 0.0833333358,
                  "sizePercentY": 1.69047618,
                  "sizeType": 0,
                  "tag": 17154,
                  "touchAble": false,
                  "useMergedTexture": false,
                  "visible": true,
                  "width": 14,
                  "x": 0,
                  "y": -32,
                  "capInsetsHeight": 1,
                  "capInsetsWidth": 1,
                  "capInsetsX": 0,
                  "capInsetsY": 0,
                  "fileName": null,
                  "fileNameData": {
                    "path": "common/guide_line.png",
                    "plistFile": "",
                    "resourceType": 0
                  },
                  "scale9Enable": false,
                  "scale9Height": 284,
                  "scale9Width": 14
                }
              }
            ],
            "options": {
              "__type": "ImageViewSurrogate:#EditorCommon.JsonModel.Component.GUI",
              "classname": "ImageView",
              "name": "Image_touchPoint",
              "ZOrder": 0,
              "actiontag": 6,
              "anchorPointX": 0.5,
              "anchorPointY": 0.5,
              "classType": "CocoStudio.EngineAdapterWrap.CSImageView",
              "colorB": 255,
              "colorG": 255,
              "colorR": 255,
              "customProperty": "",
              "flipX": false,
              "flipY": false,
              "height": 168,
              "ignoreSize": false,
              "layoutParameter": null,
              "opacity": 255,
              "positionPercentX": 0.5,
              "positionPercentY": 0.5,
              "positionType": 0,
              "rotation": 0,
              "scaleX": 1,
              "scaleY": 1,
              "sizePercentX": 0.2625,
              "sizePercentY": 0.175,
              "sizeType": 0,
              "tag": 17135,
              "touchAble": true,
              "useMergedTexture": false,
              "visible": true,
              "width": 168,
              "x": 320,
              "y": 480,
              "capInsetsHeight": 1,
              "capInsetsWidth": 1,
              "capInsetsX": 0,
              "capInsetsY": 0,
              "fileName": null,
              "fileNameData": {
                "path": "common/transparent.png",
                "plistFile": "",
                "resourceType": 0
              },
              "scale9Enable": false,
              "scale9Height": 168,
              "scale9Width": 168
            }
          },
          {
            "classname": "ImageView",
            "name": null,
            "children": [],
            "options": {
              "__type": "ImageViewSurrogate:#EditorCommon.JsonModel.Component.GUI",
              "classname": "ImageView",
              "name": "Image_point",
              "ZOrder": 0,
              "actiontag": 36,
              "anchorPointX": 0.5,
              "anchorPointY": 1,
              "classType": "CocoStudio.EngineAdapterWrap.CSImageView",
              "colorB": 255,
              "colorG": 255,
              "colorR": 255,
              "customProperty": "",
              "flipX": false,
              "flipY": false,
              "height": 132,
              "ignoreSize": true,
              "layoutParameter": null,
              "opacity": 255,
              "positionPercentX": 0.5,
              "positionPercentY": 0.466666669,
              "positionType": 0,
              "rotation": 0,
              "scaleX": 1,
              "scaleY": 1,
              "sizePercentX": 0.15625,
              "sizePercentY": 0.1375,
              "sizeType": 0,
              "tag": 17165,
              "touchAble": false,
              "useMergedTexture": false,
              "visible": true,
              "width": 100,
              "x": 320,
              "y": 448,
              "capInsetsHeight": 1,
              "capInsetsWidth": 1,
              "capInsetsX": 0,
              "capInsetsY": 0,
              "fileName": null,
              "fileNameData": {
                "path": "common/guide_point.png",
                "plistFile": "",
                "resourceType": 0
              },
              "scale9Enable": false,
              "scale9Height": 132,
              "scale9Width": 100
            }
          },
          {
            "classname": "Label",
            "name": null,
            "children": [],
            "options": {
              "__type": "LabelSurrogate:#EditorCommon.JsonModel.Component.GUI",
              "classname": "Label",
              "name": "Label_text",
              "ZOrder": 0,
              "actiontag": 9,
              "anchorPointX": 0.5,
              "anchorPointY": 0.5,
              "classType": "CocoStudio.EngineAdapterWrap.CSLabel",
              "colorB": 2,
              "colorG": 1,
              "colorR": 36,
              "customProperty": "",
              "flipX": false,
              "flipY": false,
              "height": 90,
              "ignoreSize": false,
              "layoutParameter": null,
              "opacity": 255,
              "positionPercentX": 0.5,
              "positionPercentY": 0.416666657,
              "positionType": 0,
              "rotation": 0,
              "scaleX": 1,
              "scaleY": 1,
              "sizePercentX": 0.78125,
              "sizePercentY": 0.09375,
              "sizeType": 0,
              "tag": 17203,
              "touchAble": false,
              "useMergedTexture": false,
              "visible": false,
              "width": 500,
              "x": 320,
              "y": 400,
              "areaHeight": 90,
              "areaWidth": 500,
              "fontFile": null,
              "fontName": "",
              "fontSize": 20,
              "hAlignment": 0,
              "text": "",
              "touchScaleEnable": false,
              "vAlignment": 1
            }
          }
        ],
        "options": {
          "__type": "PanelSurrogate:#EditorCommon.JsonModel.Component.GUI",
          "classname": "Panel",
          "name": "Panel_cont",
          "ZOrder": 0,
          "actiontag": 4,
          "anchorPointX": 0,
          "anchorPointY": 0,
          "classType": "CocoStudio.EngineAdapterWrap.CSPanel",
          "colorB": 255,
          "colorG": 255,
          "colorR": 255,
          "customProperty": "",
          "flipX": false,
          "flipY": false,
          "height": 960,
          "ignoreSize": false,
          "layoutParameter": null,
          "opacity": 255,
          "positionPercentX": 0,
          "positionPercentY": 0,
          "positionType": 0,
          "rotation": 0,
          "scaleX": 1,
          "scaleY": 1,
          "sizePercentX": 1,
          "sizePercentY": 1,
          "sizeType": 0,
          "tag": 17131,
          "touchAble": false,
          "useMergedTexture": false,
          "visible": true,
          "width": 640,
          "x": 0,
          "y": 0,
          "adaptScreen": false,
          "backGroundImage": null,
          "backGroundImageData": null,
          "backGroundScale9Enable": false,
          "bgColorB": 255,
          "bgColorG": 200,
          "bgColorOpacity": 100,
          "bgColorR": 150,
          "bgEndColorB": 255,
          "bgEndColorG": 200,
          "bgEndColorR": 150,
          "bgStartColorB": 255,
          "bgStartColorG": 255,
          "bgStartColorR": 255,
          "capInsetsHeight": 1,
          "capInsetsWidth": 1,
          "capInsetsX": 0,
          "capInsetsY": 0,
          "clipAble": false,
          "colorType": 0,
          "layoutType": 0,
          "vectorX": 0,
          "vectorY": -0.5
        }
      }
    ],
    "options": {
      "__type": "PanelSurrogate:#EditorCommon.JsonModel.Component.GUI",
      "classname": "Panel",
      "name": "Panel_main",
      "ZOrder": 0,
      "actiontag": -1,
      "anchorPointX": 0,
      "anchorPointY": 0,
      "classType": "CocoStudio.EngineAdapterWrap.CSPanel",
      "colorB": 255,
      "colorG": 255,
      "colorR": 255,
      "customProperty": "",
      "flipX": false,
      "flipY": false,
      "height": 960,
      "ignoreSize": false,
      "layoutParameter": null,
      "opacity": 255,
      "positionPercentX": 0,
      "positionPercentY": 0,
      "positionType": 0,
      "rotation": 0,
      "scaleX": 1,
      "scaleY": 1,
      "sizePercentX": 1,
      "sizePercentY": 1,
      "sizeType": 0,
      "tag": 17129,
      "touchAble": true,
      "useMergedTexture": false,
      "visible": true,
      "width": 640,
      "x": 0,
      "y": 0,
      "adaptScreen": false,
      "backGroundImage": null,
      "backGroundImageData": null,
      "backGroundScale9Enable": false,
      "bgColorB": 255,
      "bgColorG": 200,
      "bgColorOpacity": 0,
      "bgColorR": 150,
      "bgEndColorB": 255,
      "bgEndColorG": 200,
      "bgEndColorR": 150,
      "bgStartColorB": 255,
      "bgStartColorG": 255,
      "bgStartColorR": 255,
      "capInsetsHeight": 1,
      "capInsetsWidth": 1,
      "capInsetsX": 0,
      "capInsetsY": 0,
      "clipAble": false,
      "colorType": 1,
      "layoutType": 0,
      "vectorX": 0,
      "vectorY": -0.5
    }
  }
}