{
  "classname": null,
  "name": null,
  "animation": {
    "classname": null,
    "name": "AnimationManager",
    "actionlist": []
  },
  "dataScale": 1,
  "designHeight": 960,
  "designWidth": 640,
  "textures": [],
  "texturesPng": [
    "common/ui_border_bar.png",
    "common/bg_1.png",
    "common/bg_2.png",
    "common/bg_3.png",
    "common/bg_4.png",
    "common/bg_5.png",
    "common/bg_6.png",
    "common/bg_7.png",
    "common/bg_8.png",
    "common/bg_9.png",
    "common/button_blue.png",
    "common/alliance_15.png",
    "common/power.png",
    "common/alliance_71.png"
  ],
  "version": "1.5.0.0",
  "widgetTree": {
    "classname": "Panel",
    "name": null,
    "children": [
      {
        "classname": "ListView",
        "name": null,
        "children": [
          {
            "classname": "Panel",
            "name": null,
            "children": [
              {
                "classname": "Panel",
                "name": null,
                "children": [
                  {
                    "classname": "ImageView",
                    "name": null,
                    "children": [],
                    "options": {
                      "__type": "ImageViewSurrogate:#EditorCommon.JsonModel.Component.GUI",
                      "classname": "ImageView",
                      "name": "ImageView_30174",
                      "ZOrder": 0,
                      "actiontag": 30174,
                      "anchorPointX": 0.5,
                      "anchorPointY": 0.5,
                      "classType": "CocoStudio.EngineAdapterWrap.CSImageView",
                      "colorB": 255,
                      "colorG": 255,
                      "colorR": 255,
                      "customProperty": "",
                      "flipX": false,
                      "flipY": false,
                      "height": 42,
                      "ignoreSize": true,
                      "layoutParameter": null,
                      "opacity": 255,
                      "positionPercentX": 0.5,
                      "positionPercentY": 0.461538464,
                      "positionType": 0,
                      "rotation": 0,
                      "scaleX": 1,
                      "scaleY": 1,
                      "sizePercentX": 0.98125,
                      "sizePercentY": 0.8076923,
                      "sizeType": 0,
                      "tag": 29565,
                      "touchAble": false,
                      "useMergedTexture": false,
                      "visible": true,
                      "width": 628,
                      "x": 320,
                      "y": 24,
                      "capInsetsHeight": 1,
                      "capInsetsWidth": 1,
                      "capInsetsX": 0,
                      "capInsetsY": 0,
                      "fileName": null,
                      "fileNameData": {
                        "path": "common/ui_border_bar.png",
                        "plistFile": "",
                        "resourceType": 0
                      },
                      "scale9Enable": false,
                      "scale9Height": 42,
                      "scale9Width": 628
                    }
                  }
                ],
                "options": {
                  "__type": "PanelSurrogate:#EditorCommon.JsonModel.Component.GUI",
                  "classname": "Panel",
                  "name": "Panel_30175",
                  "ZOrder": 0,
                  "actiontag": 30175,
                  "anchorPointX": 0,
                  "anchorPointY": 0,
                  "classType": "CocoStudio.EngineAdapterWrap.CSPanel",
                  "colorB": 255,
                  "colorG": 255,
                  "colorR": 255,
                  "customProperty": "",
                  "flipX": false,
                  "flipY": false,
                  "height": 52,
                  "ignoreSize": false,
                  "layoutParameter": null,
                  "opacity": 255,
                  "positionPercentX": 0,
                  "positionPercentY": 0,
                  "positionType": 0,
                  "rotation": 0,
                  "scaleX": 1,
                  "scaleY": 1,
                  "sizePercentX": 1,
                  "sizePercentY": 1,
                  "sizeType": 1,
                  "tag": -99,
                  "touchAble": false,
                  "useMergedTexture": false,
                  "visible": true,
                  "width": 640,
                  "x": 0,
                  "y": 0,
                  "adaptScreen": false,
                  "backGroundImage": null,
                  "backGroundImageData": null,
                  "backGroundScale9Enable": false,
                  "bgColorB": 255,
                  "bgColorG": 200,
                  "bgColorOpacity": 100,
                  "bgColorR": 150,
                  "bgEndColorB": 255,
                  "bgEndColorG": 200,
                  "bgEndColorR": 150,
                  "bgStartColorB": 255,
                  "bgStartColorG": 255,
                  "bgStartColorR": 255,
                  "capInsetsHeight": 1,
                  "capInsetsWidth": 1,
                  "capInsetsX": 0,
                  "capInsetsY": 0,
                  "clipAble": false,
                  "colorType": 0,
                  "layoutType": 0,
                  "vectorX": 0,
                  "vectorY": -0.5
                }
              },
              {
                "classname": "Panel",
                "name": null,
                "children": [
                  {
                    "classname": "Label",
                    "name": null,
                    "children": [],
                    "options": {
                      "__type": "LabelSurrogate:#EditorCommon.JsonModel.Component.GUI",
                      "classname": "Label",
                      "name": "Label_30181",
                      "ZOrder": 0,
                      "actiontag": 30181,
                      "anchorPointX": 0.5,
                      "anchorPointY": 0.5,
                      "classType": "CocoStudio.EngineAdapterWrap.CSLabel",
                      "colorB": 31,
                      "colorG": 163,
                      "colorR": 255,
                      "customProperty": "",
                      "flipX": false,
                      "flipY": false,
                      "height": 35,
                      "ignoreSize": true,
                      "layoutParameter": null,
                      "opacity": 255,
                      "positionPercentX": 0.5,
                      "positionPercentY": 0.5217391,
                      "positionType": 0,
                      "rotation": 0,
                      "scaleX": 1,
                      "scaleY": 1,
                      "sizePercentX": 0.1984375,
                      "sizePercentY": 0.760869563,
                      "sizeType": 0,
                      "tag": 29572,
                      "touchAble": false,
                      "useMergedTexture": false,
                      "visible": true,
                      "width": 127,
                      "x": 320,
                      "y": 24,
                      "areaHeight": 0,
                      "areaWidth": 0,
                      "fontFile": null,
                      "fontName": "微软雅黑",
                      "fontSize": 26,
                      "hAlignment": 0,
                      "text": "Text Label",
                      "touchScaleEnable": false,
                      "vAlignment": 0
                    }
                  }
                ],
                "options": {
                  "__type": "PanelSurrogate:#EditorCommon.JsonModel.Component.GUI",
                  "classname": "Panel",
                  "name": "Panel_30179",
                  "ZOrder": 0,
                  "actiontag": 30179,
                  "anchorPointX": 0,
                  "anchorPointY": 0,
                  "classType": "CocoStudio.EngineAdapterWrap.CSPanel",
                  "colorB": 255,
                  "colorG": 255,
                  "colorR": 255,
                  "customProperty": "",
                  "flipX": false,
                  "flipY": false,
                  "height": 46,
                  "ignoreSize": false,
                  "layoutParameter": null,
                  "opacity": 255,
                  "positionPercentX": 0,
                  "positionPercentY": 0,
                  "positionType": 0,
                  "rotation": 0,
                  "scaleX": 1,
                  "scaleY": 1,
                  "sizePercentX": 1,
                  "sizePercentY": 0.884615362,
                  "sizeType": 0,
                  "tag": 29570,
                  "touchAble": false,
                  "useMergedTexture": false,
                  "visible": true,
                  "width": 640,
                  "x": 0,
                  "y": 0,
                  "adaptScreen": false,
                  "backGroundImage": null,
                  "backGroundImageData": null,
                  "backGroundScale9Enable": false,
                  "bgColorB": 255,
                  "bgColorG": 200,
                  "bgColorOpacity": 100,
                  "bgColorR": 150,
                  "bgEndColorB": 255,
                  "bgEndColorG": 200,
                  "bgEndColorR": 150,
                  "bgStartColorB": 255,
                  "bgStartColorG": 255,
                  "bgStartColorR": 255,
                  "capInsetsHeight": 1,
                  "capInsetsWidth": 1,
                  "capInsetsX": 0,
                  "capInsetsY": 0,
                  "clipAble": false,
                  "colorType": 0,
                  "layoutType": 0,
                  "vectorX": 0,
                  "vectorY": -0.5
                }
              }
            ],
            "options": {
              "__type": "PanelSurrogate:#EditorCommon.JsonModel.Component.GUI",
              "classname": "Panel",
              "name": "Panel_30173",
              "ZOrder": 0,
              "actiontag": 30173,
              "anchorPointX": 0,
              "anchorPointY": 0,
              "classType": "CocoStudio.EngineAdapterWrap.CSPanel",
              "colorB": 255,
              "colorG": 255,
              "colorR": 255,
              "customProperty": "",
              "flipX": false,
              "flipY": false,
              "height": 52,
              "ignoreSize": false,
              "layoutParameter": {
                "classname": null,
                "name": null,
                "align": 0,
                "gravity": 2,
                "layoutEageType": 0,
                "layoutNormalHorizontal": 0,
                "layoutNormalVertical": 0,
                "layoutParentHorizontal": 0,
                "layoutParentVertical": 0,
                "marginDown": 0,
                "marginLeft": 0,
                "marginRight": 0,
                "marginTop": -734,
                "relativeName": "Panel_30173",
                "relativeToName": "ListView_30172",
                "type": 1
              },
              "opacity": 255,
              "positionPercentX": 0,
              "positionPercentY": 0.9299191,
              "positionType": 0,
              "rotation": 0,
              "scaleX": 1,
              "scaleY": 1,
              "sizePercentX": 1,
              "sizePercentY": 0.07008086,
              "sizeType": 0,
              "tag": 1213,
              "touchAble": false,
              "useMergedTexture": false,
              "visible": true,
              "width": 640,
              "x": 0,
              "y": 690,
              "adaptScreen": false,
              "backGroundImage": null,
              "backGroundImageData": null,
              "backGroundScale9Enable": false,
              "bgColorB": 255,
              "bgColorG": 200,
              "bgColorOpacity": 100,
              "bgColorR": 150,
              "bgEndColorB": 255,
              "bgEndColorG": 200,
              "bgEndColorR": 150,
              "bgStartColorB": 255,
              "bgStartColorG": 255,
              "bgStartColorR": 255,
              "capInsetsHeight": 1,
              "capInsetsWidth": 1,
              "capInsetsX": 0,
              "capInsetsY": 0,
              "clipAble": false,
              "colorType": 0,
              "layoutType": 0,
              "vectorX": 0,
              "vectorY": -0.5
            }
          },
          {
            "classname": "Panel",
            "name": null,
            "children": [
              {
                "classname": "Panel",
                "name": null,
                "children": [
                  {
                    "classname": "ImageView",
                    "name": null,
                    "children": [],
                    "options": {
                      "__type": "ImageViewSurrogate:#EditorCommon.JsonModel.Component.GUI",
                      "classname": "ImageView",
                      "name": "1",
                      "ZOrder": 2,
                      "actiontag": 8491627,
                      "anchorPointX": 1,
                      "anchorPointY": 0,
                      "classType": "CocoStudio.EngineAdapterWrap.CSImageView",
                      "colorB": 255,
                      "colorG": 255,
                      "colorR": 255,
                      "customProperty": "",
                      "flipX": false,
                      "flipY": false,
                      "height": 24,
                      "ignoreSize": true,
                      "layoutParameter": null,
                      "opacity": 255,
                      "positionPercentX": 0.046875,
                      "positionPercentY": 0.5625,
                      "positionType": 0,
                      "rotation": 0,
                      "scaleX": 1,
                      "scaleY": 1,
                      "sizePercentX": 0.0375,
                      "sizePercentY": 0.375,
                      "sizeType": 0,
                      "tag": -93,
                      "touchAble": false,
                      "useMergedTexture": false,
                      "visible": true,
                      "width": 24,
                      "x": 30,
                      "y": 36,
                      "capInsetsHeight": 1,
                      "capInsetsWidth": 1,
                      "capInsetsX": 0,
                      "capInsetsY": 0,
                      "fileName": null,
                      "fileNameData": {
                        "path": "common/bg_1.png",
                        "plistFile": "",
                        "resourceType": 0
                      },
                      "scale9Enable": false,
                      "scale9Height": 24,
                      "scale9Width": 24
                    }
                  },
                  {
                    "classname": "ImageView",
                    "name": null,
                    "children": [],
                    "options": {
                      "__type": "ImageViewSurrogate:#EditorCommon.JsonModel.Component.GUI",
                      "classname": "ImageView",
                      "name": "2",
                      "ZOrder": 1,
                      "actiontag": 63252295,
                      "anchorPointX": 0.5,
                      "anchorPointY": 0,
                      "classType": "CocoStudio.EngineAdapterWrap.CSImageView",
                      "colorB": 255,
                      "colorG": 255,
                      "colorR": 255,
                      "customProperty": "",
                      "flipX": false,
                      "flipY": false,
                      "height": 24,
                      "ignoreSize": false,
                      "layoutParameter": null,
                      "opacity": 255,
                      "positionPercentX": 0.5,
                      "positionPercentY": 0.5625,
                      "positionType": 0,
                      "rotation": 0,
                      "scaleX": 1,
                      "scaleY": 1,
                      "sizePercentX": 0.90625,
                      "sizePercentY": 0.375,
                      "sizeType": 0,
                      "tag": -91,
                      "touchAble": false,
                      "useMergedTexture": false,
                      "visible": true,
                      "width": 580,
                      "x": 320,
                      "y": 36,
                      "capInsetsHeight": 1,
                      "capInsetsWidth": 1,
                      "capInsetsX": 0,
                      "capInsetsY": 0,
                      "fileName": null,
                      "fileNameData": {
                        "path": "common/bg_2.png",
                        "plistFile": "",
                        "resourceType": 0
                      },
                      "scale9Enable": false,
                      "scale9Height": 24,
                      "scale9Width": 580
                    }
                  },
                  {
                    "classname": "ImageView",
                    "name": null,
                    "children": [],
                    "options": {
                      "__type": "ImageViewSurrogate:#EditorCommon.JsonModel.Component.GUI",
                      "classname": "ImageView",
                      "name": "3",
                      "ZOrder": 2,
                      "actiontag": 7133556,
                      "anchorPointX": 0,
                      "anchorPointY": 0,
                      "classType": "CocoStudio.EngineAdapterWrap.CSImageView",
                      "colorB": 255,
                      "colorG": 255,
                      "colorR": 255,
                      "customProperty": "",
                      "flipX": false,
                      "flipY": false,
                      "height": 24,
                      "ignoreSize": true,
                      "layoutParameter": null,
                      "opacity": 255,
                      "positionPercentX": 0.953125,
                      "positionPercentY": 0.5625,
                      "positionType": 0,
                      "rotation": 0,
                      "scaleX": 1,
                      "scaleY": 1,
                      "sizePercentX": 0.0375,
                      "sizePercentY": 0.375,
                      "sizeType": 0,
                      "tag": -93,
                      "touchAble": false,
                      "useMergedTexture": false,
                      "visible": true,
                      "width": 24,
                      "x": 610,
                      "y": 36,
                      "capInsetsHeight": 1,
                      "capInsetsWidth": 1,
                      "capInsetsX": 0,
                      "capInsetsY": 0,
                      "fileName": null,
                      "fileNameData": {
                        "path": "common/bg_3.png",
                        "plistFile": "",
                        "resourceType": 0
                      },
                      "scale9Enable": false,
                      "scale9Height": 24,
                      "scale9Width": 24
                    }
                  },
                  {
                    "classname": "ImageView",
                    "name": null,
                    "children": [],
                    "options": {
                      "__type": "ImageViewSurrogate:#EditorCommon.JsonModel.Component.GUI",
                      "classname": "ImageView",
                      "name": "4",
                      "ZOrder": 0,
                      "actiontag": 64202010,
                      "anchorPointX": 1,
                      "anchorPointY": 0.5,
                      "classType": "CocoStudio.EngineAdapterWrap.CSImageView",
                      "colorB": 255,
                      "colorG": 255,
                      "colorR": 255,
                      "customProperty": "",
                      "flipX": false,
                      "flipY": false,
                      "height": 20,
                      "ignoreSize": false,
                      "layoutParameter": null,
                      "opacity": 255,
                      "positionPercentX": 0.046875,
                      "positionPercentY": 0.40625,
                      "positionType": 0,
                      "rotation": 0,
                      "scaleX": 1,
                      "scaleY": 1,
                      "sizePercentX": 0.0375,
                      "sizePercentY": 0.3125,
                      "sizeType": 0,
                      "tag": -92,
                      "touchAble": false,
                      "useMergedTexture": false,
                      "visible": true,
                      "width": 24,
                      "x": 30,
                      "y": 26,
                      "capInsetsHeight": 1,
                      "capInsetsWidth": 1,
                      "capInsetsX": 0,
                      "capInsetsY": 0,
                      "fileName": null,
                      "fileNameData": {
                        "path": "common/bg_4.png",
                        "plistFile": "",
                        "resourceType": 0
                      },
                      "scale9Enable": false,
                      "scale9Height": 20,
                      "scale9Width": 24
                    }
                  },
                  {
                    "classname": "ImageView",
                    "name": null,
                    "children": [],
                    "options": {
                      "__type": "ImageViewSurrogate:#EditorCommon.JsonModel.Component.GUI",
                      "classname": "ImageView",
                      "name": "5",
                      "ZOrder": 0,
                      "actiontag": 40947186,
                      "anchorPointX": 0.5,
                      "anchorPointY": 0.5,
                      "classType": "CocoStudio.EngineAdapterWrap.CSImageView",
                      "colorB": 255,
                      "colorG": 255,
                      "colorR": 255,
                      "customProperty": "",
                      "flipX": false,
                      "flipY": false,
                      "height": 20,
                      "ignoreSize": false,
                      "layoutParameter": null,
                      "opacity": 255,
                      "positionPercentX": 0.5,
                      "positionPercentY": 0.40625,
                      "positionType": 0,
                      "rotation": 0,
                      "scaleX": 1,
                      "scaleY": 1,
                      "sizePercentX": 0.90625,
                      "sizePercentY": 0.3125,
                      "sizeType": 0,
                      "tag": 138863,
                      "touchAble": false,
                      "useMergedTexture": false,
                      "visible": true,
                      "width": 580,
                      "x": 320,
                      "y": 26,
                      "capInsetsHeight": 1,
                      "capInsetsWidth": 1,
                      "capInsetsX": 0,
                      "capInsetsY": 0,
                      "fileName": null,
                      "fileNameData": {
                        "path": "common/bg_5.png",
                        "plistFile": "",
                        "resourceType": 0
                      },
                      "scale9Enable": false,
                      "scale9Height": 20,
                      "scale9Width": 580
                    }
                  },
                  {
                    "classname": "ImageView",
                    "name": null,
                    "children": [],
                    "options": {
                      "__type": "ImageViewSurrogate:#EditorCommon.JsonModel.Component.GUI",
                      "classname": "ImageView",
                      "name": "6",
                      "ZOrder": 0,
                      "actiontag": 32980355,
                      "anchorPointX": 0,
                      "anchorPointY": 0.5,
                      "classType": "CocoStudio.EngineAdapterWrap.CSImageView",
                      "colorB": 255,
                      "colorG": 255,
                      "colorR": 255,
                      "customProperty": "",
                      "flipX": false,
                      "flipY": false,
                      "height": 20,
                      "ignoreSize": false,
                      "layoutParameter": null,
                      "opacity": 255,
                      "positionPercentX": 0.953125,
                      "positionPercentY": 0.40625,
                      "positionType": 0,
                      "rotation": 0,
                      "scaleX": 1,
                      "scaleY": 1,
                      "sizePercentX": 0.0375,
                      "sizePercentY": 0.3125,
                      "sizeType": 0,
                      "tag": -92,
                      "touchAble": false,
                      "useMergedTexture": false,
                      "visible": true,
                      "width": 24,
                      "x": 610,
                      "y": 26,
                      "capInsetsHeight": 1,
                      "capInsetsWidth": 1,
                      "capInsetsX": 0,
                      "capInsetsY": 0,
                      "fileName": null,
                      "fileNameData": {
                        "path": "common/bg_6.png",
                        "plistFile": "",
                        "resourceType": 0
                      },
                      "scale9Enable": false,
                      "scale9Height": 20,
                      "scale9Width": 24
                    }
                  },
                  {
                    "classname": "ImageView",
                    "name": null,
                    "children": [],
                    "options": {
                      "__type": "ImageViewSurrogate:#EditorCommon.JsonModel.Component.GUI",
                      "classname": "ImageView",
                      "name": "7",
                      "ZOrder": 0,
                      "actiontag": 28387744,
                      "anchorPointX": 1,
                      "anchorPointY": 1,
                      "classType": "CocoStudio.EngineAdapterWrap.CSImageView",
                      "colorB": 255,
                      "colorG": 255,
                      "colorR": 255,
                      "customProperty": "",
                      "flipX": false,
                      "flipY": false,
                      "height": 24,
                      "ignoreSize": true,
                      "layoutParameter": null,
                      "opacity": 255,
                      "positionPercentX": 0.046875,
                      "positionPercentY": 0.25,
                      "positionType": 0,
                      "rotation": 0,
                      "scaleX": 1,
                      "scaleY": 1,
                      "sizePercentX": 0.0375,
                      "sizePercentY": 0.375,
                      "sizeType": 0,
                      "tag": -93,
                      "touchAble": false,
                      "useMergedTexture": false,
                      "visible": true,
                      "width": 24,
                      "x": 30,
                      "y": 16,
                      "capInsetsHeight": 1,
                      "capInsetsWidth": 1,
                      "capInsetsX": 0,
                      "capInsetsY": 0,
                      "fileName": null,
                      "fileNameData": {
                        "path": "common/bg_7.png",
                        "plistFile": "",
                        "resourceType": 0
                      },
                      "scale9Enable": false,
                      "scale9Height": 24,
                      "scale9Width": 24
                    }
                  },
                  {
                    "classname": "ImageView",
                    "name": null,
                    "children": [],
                    "options": {
                      "__type": "ImageViewSurrogate:#EditorCommon.JsonModel.Component.GUI",
                      "classname": "ImageView",
                      "name": "8",
                      "ZOrder": 0,
                      "actiontag": 54163104,
                      "anchorPointX": 0.5,
                      "anchorPointY": 1,
                      "classType": "CocoStudio.EngineAdapterWrap.CSImageView",
                      "colorB": 255,
                      "colorG": 255,
                      "colorR": 255,
                      "customProperty": "",
                      "flipX": false,
                      "flipY": false,
                      "height": 24,
                      "ignoreSize": false,
                      "layoutParameter": null,
                      "opacity": 255,
                      "positionPercentX": 0.5,
                      "positionPercentY": 0.25,
                      "positionType": 0,
                      "rotation": 0,
                      "scaleX": 1,
                      "scaleY": 1,
                      "sizePercentX": 0.90625,
                      "sizePercentY": 0.375,
                      "sizeType": 0,
                      "tag": -91,
                      "touchAble": false,
                      "useMergedTexture": false,
                      "visible": true,
                      "width": 580,
                      "x": 320,
                      "y": 16,
                      "capInsetsHeight": 1,
                      "capInsetsWidth": 1,
                      "capInsetsX": 0,
                      "capInsetsY": 0,
                      "fileName": null,
                      "fileNameData": {
                        "path": "common/bg_8.png",
                        "plistFile": "",
                        "resourceType": 0
                      },
                      "scale9Enable": false,
                      "scale9Height": 24,
                      "scale9Width": 580
                    }
                  },
                  {
                    "classname": "ImageView",
                    "name": null,
                    "children": [],
                    "options": {
                      "__type": "ImageViewSurrogate:#EditorCommon.JsonModel.Component.GUI",
                      "classname": "ImageView",
                      "name": "9",
                      "ZOrder": 0,
                      "actiontag": 17705894,
                      "anchorPointX": 0,
                      "anchorPointY": 1,
                      "classType": "CocoStudio.EngineAdapterWrap.CSImageView",
                      "colorB": 255,
                      "colorG": 255,
                      "colorR": 255,
                      "customProperty": "",
                      "flipX": false,
                      "flipY": false,
                      "height": 24,
                      "ignoreSize": true,
                      "layoutParameter": null,
                      "opacity": 255,
                      "positionPercentX": 0.953125,
                      "positionPercentY": 0.25,
                      "positionType": 0,
                      "rotation": 0,
                      "scaleX": 1,
                      "scaleY": 1,
                      "sizePercentX": 0.0375,
                      "sizePercentY": 0.375,
                      "sizeType": 0,
                      "tag": -93,
                      "touchAble": false,
                      "useMergedTexture": false,
                      "visible": true,
                      "width": 24,
                      "x": 610,
                      "y": 16,
                      "capInsetsHeight": 1,
                      "capInsetsWidth": 1,
                      "capInsetsX": 0,
                      "capInsetsY": 0,
                      "fileName": null,
                      "fileNameData": {
                        "path": "common/bg_9.png",
                        "plistFile": "",
                        "resourceType": 0
                      },
                      "scale9Enable": false,
                      "scale9Height": 24,
                      "scale9Width": 24
                    }
                  }
                ],
                "options": {
                  "__type": "PanelSurrogate:#EditorCommon.JsonModel.Component.GUI",
                  "classname": "Panel",
                  "name": "Panel_21",
                  "ZOrder": 0,
                  "actiontag": 35347099,
                  "anchorPointX": 0,
                  "anchorPointY": 0,
                  "classType": "CocoStudio.EngineAdapterWrap.CSPanel",
                  "colorB": 255,
                  "colorG": 255,
                  "colorR": 255,
                  "customProperty": "",
                  "flipX": false,
                  "flipY": false,
                  "height": 64,
                  "ignoreSize": false,
                  "layoutParameter": null,
                  "opacity": 255,
                  "positionPercentX": 0,
                  "positionPercentY": 0,
                  "positionType": 0,
                  "rotation": 0,
                  "scaleX": 1,
                  "scaleY": 1,
                  "sizePercentX": 1,
                  "sizePercentY": 1,
                  "sizeType": 1,
                  "tag": -99,
                  "touchAble": false,
                  "useMergedTexture": false,
                  "visible": true,
                  "width": 640,
                  "x": 0,
                  "y": 0,
                  "adaptScreen": false,
                  "backGroundImage": null,
                  "backGroundImageData": null,
                  "backGroundScale9Enable": false,
                  "bgColorB": 255,
                  "bgColorG": 200,
                  "bgColorOpacity": 100,
                  "bgColorR": 150,
                  "bgEndColorB": 255,
                  "bgEndColorG": 200,
                  "bgEndColorR": 150,
                  "bgStartColorB": 255,
                  "bgStartColorG": 255,
                  "bgStartColorR": 255,
                  "capInsetsHeight": 1,
                  "capInsetsWidth": 1,
                  "capInsetsX": 0,
                  "capInsetsY": 0,
                  "clipAble": false,
                  "colorType": 0,
                  "layoutType": 0,
                  "vectorX": 0,
                  "vectorY": -0.5
                }
              },
              {
                "classname": "Panel",
                "name": null,
                "children": [
                  {
                    "classname": "ImageView",
                    "name": null,
                    "children": [
                      {
                        "classname": "Label",
                        "name": null,
                        "children": [],
                        "options": {
                          "__type": "LabelSurrogate:#EditorCommon.JsonModel.Component.GUI",
                          "classname": "Label",
                          "name": "Label_4",
                          "ZOrder": 0,
                          "actiontag": 4,
                          "anchorPointX": 0.5,
                          "anchorPointY": 0.5,
                          "classType": "CocoStudio.EngineAdapterWrap.CSLabel",
                          "colorB": 255,
                          "colorG": 255,
                          "colorR": 255,
                          "customProperty": "",
                          "flipX": false,
                          "flipY": false,
                          "height": 30,
                          "ignoreSize": true,
                          "layoutParameter": null,
                          "opacity": 255,
                          "positionPercentX": 0,
                          "positionPercentY": 0,
                          "positionType": 0,
                          "rotation": 0,
                          "scaleX": 1,
                          "scaleY": 1,
                          "sizePercentX": 0.7361111,
                          "sizePercentY": 0.625,
                          "sizeType": 0,
                          "tag": 63190,
                          "touchAble": false,
                          "useMergedTexture": false,
                          "visible": true,
                          "width": 106,
                          "x": 0,
                          "y": 0,
                          "areaHeight": 0,
                          "areaWidth": 0,
                          "fontFile": null,
                          "fontName": "微软雅黑",
                          "fontSize": 22,
                          "hAlignment": 0,
                          "text": "Text Label",
                          "touchScaleEnable": false,
                          "vAlignment": 0
                        }
                      }
                    ],
                    "options": {
                      "__type": "ImageViewSurrogate:#EditorCommon.JsonModel.Component.GUI",
                      "classname": "ImageView",
                      "name": "ImageView_30186",
                      "ZOrder": 0,
                      "actiontag": 30186,
                      "anchorPointX": 0.5,
                      "anchorPointY": 0.5,
                      "classType": "CocoStudio.EngineAdapterWrap.CSImageView",
                      "colorB": 255,
                      "colorG": 255,
                      "colorR": 255,
                      "customProperty": "",
                      "flipX": false,
                      "flipY": false,
                      "height": 48,
                      "ignoreSize": false,
                      "layoutParameter": null,
                      "opacity": 255,
                      "positionPercentX": 0.84375,
                      "positionPercentY": 0.46875,
                      "positionType": 0,
                      "rotation": 0,
                      "scaleX": 1,
                      "scaleY": 1,
                      "sizePercentX": 0.225,
                      "sizePercentY": 0.75,
                      "sizeType": 0,
                      "tag": 29577,
                      "touchAble": true,
                      "useMergedTexture": false,
                      "visible": true,
                      "width": 144,
                      "x": 540,
                      "y": 30,
                      "capInsetsHeight": 1,
                      "capInsetsWidth": 1,
                      "capInsetsX": 0,
                      "capInsetsY": 0,
                      "fileName": null,
                      "fileNameData": {
                        "path": "common/button_blue.png",
                        "plistFile": "",
                        "resourceType": 0
                      },
                      "scale9Enable": false,
                      "scale9Height": 48,
                      "scale9Width": 144
                    }
                  },
                  {
                    "classname": "ImageView",
                    "name": null,
                    "children": [],
                    "options": {
                      "__type": "ImageViewSurrogate:#EditorCommon.JsonModel.Component.GUI",
                      "classname": "ImageView",
                      "name": "ImageView_30189",
                      "ZOrder": 0,
                      "actiontag": 30189,
                      "anchorPointX": 0.5,
                      "anchorPointY": 0.5,
                      "classType": "CocoStudio.EngineAdapterWrap.CSImageView",
                      "colorB": 255,
                      "colorG": 255,
                      "colorR": 255,
                      "customProperty": "",
                      "flipX": false,
                      "flipY": false,
                      "height": 44,
                      "ignoreSize": false,
                      "layoutParameter": null,
                      "opacity": 255,
                      "positionPercentX": 0.1125,
                      "positionPercentY": 0.46875,
                      "positionType": 0,
                      "rotation": 0,
                      "scaleX": 1,
                      "scaleY": 1,
                      "sizePercentX": 0.0625,
                      "sizePercentY": 0.6875,
                      "sizeType": 0,
                      "tag": 29580,
                      "touchAble": false,
                      "useMergedTexture": false,
                      "visible": true,
                      "width": 40,
                      "x": 72,
                      "y": 30,
                      "capInsetsHeight": 1,
                      "capInsetsWidth": 1,
                      "capInsetsX": 0,
                      "capInsetsY": 0,
                      "fileName": null,
                      "fileNameData": {
                        "path": "common/alliance_15.png",
                        "plistFile": "",
                        "resourceType": 0
                      },
                      "scale9Enable": false,
                      "scale9Height": 44,
                      "scale9Width": 40
                    }
                  },
                  {
                    "classname": "Label",
                    "name": null,
                    "children": [],
                    "options": {
                      "__type": "LabelSurrogate:#EditorCommon.JsonModel.Component.GUI",
                      "classname": "Label",
                      "name": "Label_30190",
                      "ZOrder": 0,
                      "actiontag": 30190,
                      "anchorPointX": 0,
                      "anchorPointY": 0.5,
                      "classType": "CocoStudio.EngineAdapterWrap.CSLabel",
                      "colorB": 19,
                      "colorG": 140,
                      "colorR": 252,
                      "customProperty": "",
                      "flipX": false,
                      "flipY": false,
                      "height": 30,
                      "ignoreSize": true,
                      "layoutParameter": null,
                      "opacity": 255,
                      "positionPercentX": 0.1640625,
                      "positionPercentY": 0.46875,
                      "positionType": 0,
                      "rotation": 0,
                      "scaleX": 1,
                      "scaleY": 1,
                      "sizePercentX": 0.165625,
                      "sizePercentY": 0.46875,
                      "sizeType": 0,
                      "tag": 29581,
                      "touchAble": false,
                      "useMergedTexture": false,
                      "visible": true,
                      "width": 106,
                      "x": 105,
                      "y": 30,
                      "areaHeight": 0,
                      "areaWidth": 0,
                      "fontFile": null,
                      "fontName": "微软雅黑",
                      "fontSize": 22,
                      "hAlignment": 0,
                      "text": "Text Label",
                      "touchScaleEnable": false,
                      "vAlignment": 0
                    }
                  },
                  {
                    "classname": "ImageView",
                    "name": null,
                    "children": [],
                    "options": {
                      "__type": "ImageViewSurrogate:#EditorCommon.JsonModel.Component.GUI",
                      "classname": "ImageView",
                      "name": "ImageView_30193",
                      "ZOrder": 0,
                      "actiontag": 30193,
                      "anchorPointX": 0.5,
                      "anchorPointY": 0.5,
                      "classType": "CocoStudio.EngineAdapterWrap.CSImageView",
                      "colorB": 255,
                      "colorG": 255,
                      "colorR": 255,
                      "customProperty": "",
                      "flipX": false,
                      "flipY": false,
                      "height": 34,
                      "ignoreSize": true,
                      "layoutParameter": null,
                      "opacity": 255,
                      "positionPercentX": 0.465625,
                      "positionPercentY": 0.46875,
                      "positionType": 0,
                      "rotation": 0,
                      "scaleX": 1,
                      "scaleY": 1,
                      "sizePercentX": 0.053125,
                      "sizePercentY": 0.53125,
                      "sizeType": 0,
                      "tag": 29584,
                      "touchAble": false,
                      "useMergedTexture": false,
                      "visible": true,
                      "width": 34,
                      "x": 298,
                      "y": 30,
                      "capInsetsHeight": 1,
                      "capInsetsWidth": 1,
                      "capInsetsX": 0,
                      "capInsetsY": 0,
                      "fileName": null,
                      "fileNameData": {
                        "path": "common/power.png",
                        "plistFile": "",
                        "resourceType": 0
                      },
                      "scale9Enable": false,
                      "scale9Height": 34,
                      "scale9Width": 34
                    }
                  },
                  {
                    "classname": "Label",
                    "name": null,
                    "children": [],
                    "options": {
                      "__type": "LabelSurrogate:#EditorCommon.JsonModel.Component.GUI",
                      "classname": "Label",
                      "name": "Label_30194",
                      "ZOrder": 0,
                      "actiontag": 30194,
                      "anchorPointX": 0,
                      "anchorPointY": 0.5,
                      "classType": "CocoStudio.EngineAdapterWrap.CSLabel",
                      "colorB": 223,
                      "colorG": 241,
                      "colorR": 245,
                      "customProperty": "",
                      "flipX": false,
                      "flipY": false,
                      "height": 30,
                      "ignoreSize": true,
                      "layoutParameter": null,
                      "opacity": 255,
                      "positionPercentX": 0.5171875,
                      "positionPercentY": 0.46875,
                      "positionType": 0,
                      "rotation": 0,
                      "scaleX": 1,
                      "scaleY": 1,
                      "sizePercentX": 0.165625,
                      "sizePercentY": 0.46875,
                      "sizeType": 0,
                      "tag": 29585,
                      "touchAble": false,
                      "useMergedTexture": false,
                      "visible": true,
                      "width": 106,
                      "x": 331,
                      "y": 30,
                      "areaHeight": 0,
                      "areaWidth": 0,
                      "fontFile": null,
                      "fontName": "微软雅黑",
                      "fontSize": 22,
                      "hAlignment": 0,
                      "text": "Text Label",
                      "touchScaleEnable": false,
                      "vAlignment": 0
                    }
                  },
                  {
                    "classname": "ImageView",
                    "name": null,
                    "children": [],
                    "options": {
                      "__type": "ImageViewSurrogate:#EditorCommon.JsonModel.Component.GUI",
                      "classname": "ImageView",
                      "name": "Image_11",
                      "ZOrder": 0,
                      "actiontag": 49635175,
                      "anchorPointX": 0.5,
                      "anchorPointY": 0.5,
                      "classType": "CocoStudio.EngineAdapterWrap.CSImageView",
                      "colorB": 255,
                      "colorG": 255,
                      "colorR": 255,
                      "customProperty": "",
                      "flipX": false,
                      "flipY": false,
                      "height": 36,
                      "ignoreSize": true,
                      "layoutParameter": null,
                      "opacity": 255,
                      "positionPercentX": 0.046875,
                      "positionPercentY": 0.46875,
                      "positionType": 0,
                      "rotation": 0,
                      "scaleX": 1,
                      "scaleY": 1,
                      "sizePercentX": 0.125,
                      "sizePercentY": 1.25,
                      "sizeType": 0,
                      "tag": 153244,
                      "touchAble": false,
                      "useMergedTexture": false,
                      "visible": false,
                      "width": 36,
                      "x": 30,
                      "y": 30,
                      "capInsetsHeight": 1,
                      "capInsetsWidth": 1,
                      "capInsetsX": 0,
                      "capInsetsY": 0,
                      "fileName": null,
                      "fileNameData": {
                        "path": "common/alliance_71.png",
                        "plistFile": "",
                        "resourceType": 0
                      },
                      "scale9Enable": false,
                      "scale9Height": 36,
                      "scale9Width": 36
                    }
                  }
                ],
                "options": {
                  "__type": "PanelSurrogate:#EditorCommon.JsonModel.Component.GUI",
                  "classname": "Panel",
                  "name": "Panel_30185",
                  "ZOrder": 0,
                  "actiontag": 30185,
                  "anchorPointX": 0,
                  "anchorPointY": 0,
                  "classType": "CocoStudio.EngineAdapterWrap.CSPanel",
                  "colorB": 255,
                  "colorG": 255,
                  "colorR": 255,
                  "customProperty": "",
                  "flipX": false,
                  "flipY": false,
                  "height": 64,
                  "ignoreSize": false,
                  "layoutParameter": null,
                  "opacity": 255,
                  "positionPercentX": 0,
                  "positionPercentY": 0,
                  "positionType": 0,
                  "rotation": 0,
                  "scaleX": 1,
                  "scaleY": 1,
                  "sizePercentX": 1,
                  "sizePercentY": 1,
                  "sizeType": 1,
                  "tag": 29576,
                  "touchAble": false,
                  "useMergedTexture": false,
                  "visible": true,
                  "width": 640,
                  "x": 0,
                  "y": 0,
                  "adaptScreen": false,
                  "backGroundImage": null,
                  "backGroundImageData": null,
                  "backGroundScale9Enable": false,
                  "bgColorB": 255,
                  "bgColorG": 200,
                  "bgColorOpacity": 100,
                  "bgColorR": 150,
                  "bgEndColorB": 255,
                  "bgEndColorG": 200,
                  "bgEndColorR": 150,
                  "bgStartColorB": 255,
                  "bgStartColorG": 255,
                  "bgStartColorR": 255,
                  "capInsetsHeight": 1,
                  "capInsetsWidth": 1,
                  "capInsetsX": 0,
                  "capInsetsY": 0,
                  "clipAble": false,
                  "colorType": 0,
                  "layoutType": 0,
                  "vectorX": 0,
                  "vectorY": -0.5
                }
              }
            ],
            "options": {
              "__type": "PanelSurrogate:#EditorCommon.JsonModel.Component.GUI",
              "classname": "Panel",
              "name": "Panel_30177",
              "ZOrder": 1,
              "actiontag": 30177,
              "anchorPointX": 0,
              "anchorPointY": 0,
              "classType": "CocoStudio.EngineAdapterWrap.CSPanel",
              "colorB": 255,
              "colorG": 255,
              "colorR": 255,
              "customProperty": "",
              "flipX": false,
              "flipY": false,
              "height": 64,
              "ignoreSize": false,
              "layoutParameter": {
                "classname": null,
                "name": null,
                "align": 0,
                "gravity": 2,
                "layoutEageType": 0,
                "layoutNormalHorizontal": 0,
                "layoutNormalVertical": 0,
                "layoutParentHorizontal": 0,
                "layoutParentVertical": 0,
                "marginDown": 0,
                "marginLeft": -639,
                "marginRight": 0,
                "marginTop": -558,
                "relativeName": "Panel_30177",
                "relativeToName": "ListView_30172",
                "type": 1
              },
              "opacity": 255,
              "positionPercentX": 0,
              "positionPercentY": 0.8436658,
              "positionType": 0,
              "rotation": 0,
              "scaleX": 1,
              "scaleY": 1,
              "sizePercentX": 1,
              "sizePercentY": 0.08625337,
              "sizeType": 0,
              "tag": 29568,
              "touchAble": false,
              "useMergedTexture": false,
              "visible": true,
              "width": 640,
              "x": 0,
              "y": 626,
              "adaptScreen": false,
              "backGroundImage": null,
              "backGroundImageData": null,
              "backGroundScale9Enable": false,
              "bgColorB": 255,
              "bgColorG": 200,
              "bgColorOpacity": 100,
              "bgColorR": 150,
              "bgEndColorB": 255,
              "bgEndColorG": 200,
              "bgEndColorR": 150,
              "bgStartColorB": 255,
              "bgStartColorG": 255,
              "bgStartColorR": 255,
              "capInsetsHeight": 1,
              "capInsetsWidth": 1,
              "capInsetsX": 0,
              "capInsetsY": 0,
              "clipAble": false,
              "colorType": 0,
              "layoutType": 0,
              "vectorX": 0,
              "vectorY": -0.5
            }
          }
        ],
        "options": {
          "__type": "ListViewSurrogate:#EditorCommon.JsonModel.Component.GUI",
          "classname": "ListView",
          "name": "ListView_30172",
          "ZOrder": 0,
          "actiontag": 30172,
          "anchorPointX": 0,
          "anchorPointY": 0,
          "classType": "CocoStudio.EngineAdapterWrap.CSListView",
          "colorB": 255,
          "colorG": 255,
          "colorR": 255,
          "customProperty": "",
          "flipX": false,
          "flipY": false,
          "height": 742,
          "ignoreSize": false,
          "layoutParameter": null,
          "opacity": 255,
          "positionPercentX": 0,
          "positionPercentY": 0.14791666,
          "positionType": 0,
          "rotation": 0,
          "scaleX": 1,
          "scaleY": 1,
          "sizePercentX": 1,
          "sizePercentY": 0.7729167,
          "sizeType": 0,
          "tag": -999,
          "touchAble": true,
          "useMergedTexture": false,
          "visible": true,
          "width": 640,
          "x": 0,
          "y": 142,
          "backGroundImage": null,
          "backGroundImageData": null,
          "backGroundScale9Enable": false,
          "bgColorB": 255,
          "bgColorG": 150,
          "bgColorOpacity": 100,
          "bgColorR": 150,
          "bgEndColorB": 255,
          "bgEndColorG": 150,
          "bgEndColorR": 150,
          "bgStartColorB": 255,
          "bgStartColorG": 255,
          "bgStartColorR": 255,
          "bounceEnable": false,
          "capInsetsHeight": 1,
          "capInsetsWidth": 1,
          "capInsetsX": 0,
          "capInsetsY": 0,
          "clipAble": true,
          "colorType": 0,
          "direction": 1,
          "editorClipAble": false,
          "gravity": 0,
          "innerHeight": 0,
          "innerWidth": 0,
          "itemMargin": 0,
          "vectorX": 0,
          "vectorY": -0.5
        }
      }
    ],
    "options": {
      "__type": "PanelSurrogate:#EditorCommon.JsonModel.Component.GUI",
      "classname": "Panel",
      "name": "Panel_main",
      "ZOrder": 0,
      "actiontag": -1,
      "anchorPointX": 0,
      "anchorPointY": 0,
      "classType": "CocoStudio.EngineAdapterWrap.CSPanel",
      "colorB": 255,
      "colorG": 255,
      "colorR": 255,
      "customProperty": "",
      "flipX": false,
      "flipY": false,
      "height": 960,
      "ignoreSize": false,
      "layoutParameter": null,
      "opacity": 255,
      "positionPercentX": 0,
      "positionPercentY": 0,
      "positionType": 0,
      "rotation": 0,
      "scaleX": 1,
      "scaleY": 1,
      "sizePercentX": 0,
      "sizePercentY": 0,
      "sizeType": 0,
      "tag": 29561,
      "touchAble": false,
      "useMergedTexture": false,
      "visible": true,
      "width": 640,
      "x": 0,
      "y": 0,
      "adaptScreen": false,
      "backGroundImage": null,
      "backGroundImageData": null,
      "backGroundScale9Enable": false,
      "bgColorB": 255,
      "bgColorG": 200,
      "bgColorOpacity": 0,
      "bgColorR": 150,
      "bgEndColorB": 255,
      "bgEndColorG": 200,
      "bgEndColorR": 150,
      "bgStartColorB": 255,
      "bgStartColorG": 255,
      "bgStartColorR": 255,
      "capInsetsHeight": 1,
      "capInsetsWidth": 1,
      "capInsetsX": 0,
      "capInsetsY": 0,
      "clipAble": false,
      "colorType": 1,
      "layoutType": 0,
      "vectorX": 0,
      "vectorY": -0.5
    }
  }
}