{
  "classname": null,
  "name": null,
  "animation": {
    "classname": null,
    "name": "AnimationManager",
    "actionlist": []
  },
  "dataScale": 1,
  "designHeight": 960,
  "designWidth": 640,
  "textures": [],
  "texturesPng": [
    "common/diamond_1.png",
    "common/close.png",
    "common/mail_border_corner.png",
    "common/mail_border_horizon.png",
    "common/mail_border_vertical.png",
    "common/mail_border_center.png",
    "common/common_bg_2.png",
    "common/ui_hero_equitFrame.png",
    "common/alliance_55.png",
    "common/power.png",
    "common/button_blue.png"
  ],
  "version": "1.5.0.0",
  "widgetTree": {
    "classname": "Panel",
    "name": null,
    "children": [
      {
        "classname": "Panel",
        "name": null,
        "children": [
          {
            "classname": "ImageView",
            "name": null,
            "children": [],
            "options": {
              "__type": "ImageViewSurrogate:#EditorCommon.JsonModel.Component.GUI",
              "classname": "ImageView",
              "name": "Image_3",
              "ZOrder": 0,
              "actiontag": 3,
              "anchorPointX": 0,
              "anchorPointY": 0,
              "classType": "CocoStudio.EngineAdapterWrap.CSImageView",
              "colorB": 255,
              "colorG": 255,
              "colorR": 255,
              "customProperty": "",
              "flipX": false,
              "flipY": false,
              "height": 904,
              "ignoreSize": true,
              "layoutParameter": null,
              "opacity": 255,
              "positionPercentX": 0,
              "positionPercentY": 0.03125,
              "positionType": 0,
              "rotation": 0,
              "scaleX": 1,
              "scaleY": 1,
              "sizePercentX": 0.9875,
              "sizePercentY": 0.941666663,
              "sizeType": 0,
              "tag": 92657,
              "touchAble": false,
              "useMergedTexture": false,
              "visible": true,
              "width": 632,
              "x": 0,
              "y": 30,
              "capInsetsHeight": 1,
              "capInsetsWidth": 1,
              "capInsetsX": 0,
              "capInsetsY": 0,
              "fileName": null,
              "fileNameData": {
                "path": "common/diamond_1.png",
                "plistFile": "",
                "resourceType": 0
              },
              "scale9Enable": false,
              "scale9Height": 904,
              "scale9Width": 632
            }
          }
        ],
        "options": {
          "__type": "PanelSurrogate:#EditorCommon.JsonModel.Component.GUI",
          "classname": "Panel",
          "name": "Panel_2",
          "ZOrder": 0,
          "actiontag": 2,
          "anchorPointX": 0,
          "anchorPointY": 0,
          "classType": "CocoStudio.EngineAdapterWrap.CSPanel",
          "colorB": 255,
          "colorG": 255,
          "colorR": 255,
          "customProperty": "",
          "flipX": false,
          "flipY": false,
          "height": 960,
          "ignoreSize": false,
          "layoutParameter": null,
          "opacity": 255,
          "positionPercentX": 0,
          "positionPercentY": 0,
          "positionType": 0,
          "rotation": 0,
          "scaleX": 1,
          "scaleY": 1,
          "sizePercentX": 1,
          "sizePercentY": 1,
          "sizeType": 1,
          "tag": -99,
          "touchAble": false,
          "useMergedTexture": false,
          "visible": true,
          "width": 640,
          "x": 0,
          "y": 0,
          "adaptScreen": false,
          "backGroundImage": null,
          "backGroundImageData": null,
          "backGroundScale9Enable": false,
          "bgColorB": 255,
          "bgColorG": 200,
          "bgColorOpacity": 100,
          "bgColorR": 150,
          "bgEndColorB": 255,
          "bgEndColorG": 200,
          "bgEndColorR": 150,
          "bgStartColorB": 255,
          "bgStartColorG": 255,
          "bgStartColorR": 255,
          "capInsetsHeight": 1,
          "capInsetsWidth": 1,
          "capInsetsX": 0,
          "capInsetsY": 0,
          "clipAble": false,
          "colorType": 0,
          "layoutType": 0,
          "vectorX": 0,
          "vectorY": -0.5
        }
      },
      {
        "classname": "Panel",
        "name": null,
        "children": [
          {
            "classname": "ImageView",
            "name": null,
            "children": [],
            "options": {
              "__type": "ImageViewSurrogate:#EditorCommon.JsonModel.Component.GUI",
              "classname": "ImageView",
              "name": "Image_5",
              "ZOrder": 0,
              "actiontag": 5,
              "anchorPointX": 1,
              "anchorPointY": 1,
              "classType": "CocoStudio.EngineAdapterWrap.CSImageView",
              "colorB": 255,
              "colorG": 255,
              "colorR": 255,
              "customProperty": "",
              "flipX": false,
              "flipY": false,
              "height": 52,
              "ignoreSize": true,
              "layoutParameter": null,
              "opacity": 255,
              "positionPercentX": 0.915625,
              "positionPercentY": 0.925,
              "positionType": 0,
              "rotation": 0,
              "scaleX": 1,
              "scaleY": 1,
              "sizePercentX": 0.08125,
              "sizePercentY": 0.0541666672,
              "sizeType": 0,
              "tag": 92659,
              "touchAble": true,
              "useMergedTexture": false,
              "visible": true,
              "width": 52,
              "x": 586,
              "y": 888,
              "capInsetsHeight": 1,
              "capInsetsWidth": 1,
              "capInsetsX": 0,
              "capInsetsY": 0,
              "fileName": null,
              "fileNameData": {
                "path": "common/close.png",
                "plistFile": "",
                "resourceType": 0
              },
              "scale9Enable": false,
              "scale9Height": 52,
              "scale9Width": 52
            }
          },
          {
            "classname": "Label",
            "name": null,
            "children": [],
            "options": {
              "__type": "LabelSurrogate:#EditorCommon.JsonModel.Component.GUI",
              "classname": "Label",
              "name": "Label_31",
              "ZOrder": 0,
              "actiontag": 31,
              "anchorPointX": 0.5,
              "anchorPointY": 0.5,
              "classType": "CocoStudio.EngineAdapterWrap.CSLabel",
              "colorB": 62,
              "colorG": 238,
              "colorR": 235,
              "customProperty": "",
              "flipX": false,
              "flipY": false,
              "height": 39,
              "ignoreSize": true,
              "layoutParameter": null,
              "opacity": 255,
              "positionPercentX": 0.5,
              "positionPercentY": 0.870833337,
              "positionType": 0,
              "rotation": 0,
              "scaleX": 1,
              "scaleY": 1,
              "sizePercentX": 0.2265625,
              "sizePercentY": 0.040625,
              "sizeType": 0,
              "tag": 92682,
              "touchAble": false,
              "useMergedTexture": false,
              "visible": true,
              "width": 145,
              "x": 320,
              "y": 836,
              "areaHeight": 0,
              "areaWidth": 0,
              "fontFile": null,
              "fontName": "微软雅黑",
              "fontSize": 30,
              "hAlignment": 0,
              "text": "Text Label",
              "touchScaleEnable": false,
              "vAlignment": 0
            }
          },
          {
            "classname": "Label",
            "name": null,
            "children": [],
            "options": {
              "__type": "LabelSurrogate:#EditorCommon.JsonModel.Component.GUI",
              "classname": "Label",
              "name": "Label_31_0",
              "ZOrder": 0,
              "actiontag": 33,
              "anchorPointX": 0.5,
              "anchorPointY": 0.5,
              "classType": "CocoStudio.EngineAdapterWrap.CSLabel",
              "colorB": 223,
              "colorG": 241,
              "colorR": 245,
              "customProperty": "",
              "flipX": false,
              "flipY": false,
              "height": 30,
              "ignoreSize": true,
              "layoutParameter": null,
              "opacity": 255,
              "positionPercentX": 0.5,
              "positionPercentY": 0.8229167,
              "positionType": 0,
              "rotation": 0,
              "scaleX": 1,
              "scaleY": 1,
              "sizePercentX": 0.165625,
              "sizePercentY": 0.03125,
              "sizeType": 0,
              "tag": 92684,
              "touchAble": false,
              "useMergedTexture": false,
              "visible": true,
              "width": 106,
              "x": 320,
              "y": 790,
              "areaHeight": 0,
              "areaWidth": 0,
              "fontFile": null,
              "fontName": "微软雅黑",
              "fontSize": 22,
              "hAlignment": 0,
              "text": "Text Label",
              "touchScaleEnable": false,
              "vAlignment": 0
            }
          }
        ],
        "options": {
          "__type": "PanelSurrogate:#EditorCommon.JsonModel.Component.GUI",
          "classname": "Panel",
          "name": "Panel_4",
          "ZOrder": 0,
          "actiontag": 4,
          "anchorPointX": 0,
          "anchorPointY": 0,
          "classType": "CocoStudio.EngineAdapterWrap.CSPanel",
          "colorB": 255,
          "colorG": 255,
          "colorR": 255,
          "customProperty": "",
          "flipX": false,
          "flipY": false,
          "height": 960,
          "ignoreSize": false,
          "layoutParameter": null,
          "opacity": 255,
          "positionPercentX": 0,
          "positionPercentY": 0,
          "positionType": 0,
          "rotation": 0,
          "scaleX": 1,
          "scaleY": 1,
          "sizePercentX": 1,
          "sizePercentY": 1,
          "sizeType": 1,
          "tag": 92658,
          "touchAble": false,
          "useMergedTexture": false,
          "visible": true,
          "width": 640,
          "x": 0,
          "y": 0,
          "adaptScreen": false,
          "backGroundImage": null,
          "backGroundImageData": null,
          "backGroundScale9Enable": false,
          "bgColorB": 255,
          "bgColorG": 200,
          "bgColorOpacity": 100,
          "bgColorR": 150,
          "bgEndColorB": 255,
          "bgEndColorG": 200,
          "bgEndColorR": 150,
          "bgStartColorB": 255,
          "bgStartColorG": 255,
          "bgStartColorR": 255,
          "capInsetsHeight": 1,
          "capInsetsWidth": 1,
          "capInsetsX": 0,
          "capInsetsY": 0,
          "clipAble": false,
          "colorType": 0,
          "layoutType": 0,
          "vectorX": 0,
          "vectorY": -0.5
        }
      },
      {
        "classname": "ListView",
        "name": null,
        "children": [
          {
            "classname": "Panel",
            "name": null,
            "children": [
              {
                "classname": "Panel",
                "name": null,
                "children": [
                  {
                    "classname": "ImageView",
                    "name": null,
                    "children": [],
                    "options": {
                      "__type": "ImageViewSurrogate:#EditorCommon.JsonModel.Component.GUI",
                      "classname": "ImageView",
                      "name": "1",
                      "ZOrder": 2,
                      "actiontag": 20,
                      "anchorPointX": 0,
                      "anchorPointY": 1,
                      "classType": "CocoStudio.EngineAdapterWrap.CSImageView",
                      "colorB": 255,
                      "colorG": 255,
                      "colorR": 255,
                      "customProperty": "",
                      "flipX": false,
                      "flipY": false,
                      "height": 24,
                      "ignoreSize": true,
                      "layoutParameter": null,
                      "opacity": 255,
                      "positionPercentX": 0.0533333346,
                      "positionPercentY": 1,
                      "positionType": 0,
                      "rotation": 0,
                      "scaleX": 1,
                      "scaleY": 1,
                      "sizePercentX": 0.04,
                      "sizePercentY": 0.122448981,
                      "sizeType": 0,
                      "tag": -93,
                      "touchAble": false,
                      "useMergedTexture": false,
                      "visible": true,
                      "width": 24,
                      "x": 32,
                      "y": 196,
                      "capInsetsHeight": 1,
                      "capInsetsWidth": 1,
                      "capInsetsX": 0,
                      "capInsetsY": 0,
                      "fileName": null,
                      "fileNameData": {
                        "path": "common/mail_border_corner.png",
                        "plistFile": "",
                        "resourceType": 0
                      },
                      "scale9Enable": false,
                      "scale9Height": 24,
                      "scale9Width": 24
                    }
                  },
                  {
                    "classname": "ImageView",
                    "name": null,
                    "children": [],
                    "options": {
                      "__type": "ImageViewSurrogate:#EditorCommon.JsonModel.Component.GUI",
                      "classname": "ImageView",
                      "name": "2",
                      "ZOrder": 1,
                      "actiontag": 21,
                      "anchorPointX": 0.5,
                      "anchorPointY": 1,
                      "classType": "CocoStudio.EngineAdapterWrap.CSImageView",
                      "colorB": 255,
                      "colorG": 255,
                      "colorR": 255,
                      "customProperty": "",
                      "flipX": false,
                      "flipY": false,
                      "height": 24,
                      "ignoreSize": false,
                      "layoutParameter": null,
                      "opacity": 255,
                      "positionPercentX": 0.5,
                      "positionPercentY": 1,
                      "positionType": 0,
                      "rotation": 0,
                      "scaleX": 1,
                      "scaleY": 1,
                      "sizePercentX": 0.863333344,
                      "sizePercentY": 0.122448981,
                      "sizeType": 0,
                      "tag": -91,
                      "touchAble": false,
                      "useMergedTexture": false,
                      "visible": true,
                      "width": 518,
                      "x": 300,
                      "y": 196,
                      "capInsetsHeight": 1,
                      "capInsetsWidth": 1,
                      "capInsetsX": 0,
                      "capInsetsY": 0,
                      "fileName": null,
                      "fileNameData": {
                        "path": "common/mail_border_horizon.png",
                        "plistFile": "",
                        "resourceType": 0
                      },
                      "scale9Enable": false,
                      "scale9Height": 24,
                      "scale9Width": 518
                    }
                  },
                  {
                    "classname": "ImageView",
                    "name": null,
                    "children": [],
                    "options": {
                      "__type": "ImageViewSurrogate:#EditorCommon.JsonModel.Component.GUI",
                      "classname": "ImageView",
                      "name": "3",
                      "ZOrder": 2,
                      "actiontag": 23,
                      "anchorPointX": 1,
                      "anchorPointY": 1,
                      "classType": "CocoStudio.EngineAdapterWrap.CSImageView",
                      "colorB": 255,
                      "colorG": 255,
                      "colorR": 255,
                      "customProperty": "",
                      "flipX": true,
                      "flipY": false,
                      "height": 24,
                      "ignoreSize": true,
                      "layoutParameter": null,
                      "opacity": 255,
                      "positionPercentX": 0.946666658,
                      "positionPercentY": 1,
                      "positionType": 0,
                      "rotation": 0,
                      "scaleX": 1,
                      "scaleY": 1,
                      "sizePercentX": 0.04,
                      "sizePercentY": 0.122448981,
                      "sizeType": 0,
                      "tag": -93,
                      "touchAble": false,
                      "useMergedTexture": false,
                      "visible": true,
                      "width": 24,
                      "x": 568,
                      "y": 196,
                      "capInsetsHeight": 1,
                      "capInsetsWidth": 1,
                      "capInsetsX": 0,
                      "capInsetsY": 0,
                      "fileName": null,
                      "fileNameData": {
                        "path": "common/mail_border_corner.png",
                        "plistFile": "",
                        "resourceType": 0
                      },
                      "scale9Enable": false,
                      "scale9Height": 24,
                      "scale9Width": 24
                    }
                  },
                  {
                    "classname": "ImageView",
                    "name": null,
                    "children": [],
                    "options": {
                      "__type": "ImageViewSurrogate:#EditorCommon.JsonModel.Component.GUI",
                      "classname": "ImageView",
                      "name": "4",
                      "ZOrder": 0,
                      "actiontag": 24,
                      "anchorPointX": 0,
                      "anchorPointY": 0,
                      "classType": "CocoStudio.EngineAdapterWrap.CSImageView",
                      "colorB": 255,
                      "colorG": 255,
                      "colorR": 255,
                      "customProperty": "",
                      "flipX": false,
                      "flipY": false,
                      "height": 180,
                      "ignoreSize": false,
                      "layoutParameter": null,
                      "opacity": 255,
                      "positionPercentX": 0.0533333346,
                      "positionPercentY": 0.05102041,
                      "positionType": 0,
                      "rotation": 0,
                      "scaleX": 1,
                      "scaleY": 1,
                      "sizePercentX": 0.04,
                      "sizePercentY": 0.9183673,
                      "sizeType": 0,
                      "tag": -92,
                      "touchAble": false,
                      "useMergedTexture": false,
                      "visible": true,
                      "width": 24,
                      "x": 32,
                      "y": 10,
                      "capInsetsHeight": 1,
                      "capInsetsWidth": 1,
                      "capInsetsX": 0,
                      "capInsetsY": 0,
                      "fileName": null,
                      "fileNameData": {
                        "path": "common/mail_border_vertical.png",
                        "plistFile": "",
                        "resourceType": 0
                      },
                      "scale9Enable": false,
                      "scale9Height": 180,
                      "scale9Width": 24
                    }
                  },
                  {
                    "classname": "ImageView",
                    "name": null,
                    "children": [],
                    "options": {
                      "__type": "ImageViewSurrogate:#EditorCommon.JsonModel.Component.GUI",
                      "classname": "ImageView",
                      "name": "5",
                      "ZOrder": 0,
                      "actiontag": 26,
                      "anchorPointX": 0.5,
                      "anchorPointY": 0,
                      "classType": "CocoStudio.EngineAdapterWrap.CSImageView",
                      "colorB": 255,
                      "colorG": 255,
                      "colorR": 255,
                      "customProperty": "",
                      "flipX": false,
                      "flipY": false,
                      "height": 180,
                      "ignoreSize": false,
                      "layoutParameter": null,
                      "opacity": 255,
                      "positionPercentX": 0.5,
                      "positionPercentY": 0.05102041,
                      "positionType": 0,
                      "rotation": 0,
                      "scaleX": 1,
                      "scaleY": 1,
                      "sizePercentX": 0.863333344,
                      "sizePercentY": 0.9183673,
                      "sizeType": 0,
                      "tag": 92677,
                      "touchAble": false,
                      "useMergedTexture": false,
                      "visible": true,
                      "width": 518,
                      "x": 300,
                      "y": 10,
                      "capInsetsHeight": 1,
                      "capInsetsWidth": 1,
                      "capInsetsX": 0,
                      "capInsetsY": 0,
                      "fileName": null,
                      "fileNameData": {
                        "path": "common/mail_border_center.png",
                        "plistFile": "",
                        "resourceType": 0
                      },
                      "scale9Enable": false,
                      "scale9Height": 180,
                      "scale9Width": 518
                    }
                  },
                  {
                    "classname": "ImageView",
                    "name": null,
                    "children": [],
                    "options": {
                      "__type": "ImageViewSurrogate:#EditorCommon.JsonModel.Component.GUI",
                      "classname": "ImageView",
                      "name": "6",
                      "ZOrder": 0,
                      "actiontag": 27,
                      "anchorPointX": 1,
                      "anchorPointY": 0,
                      "classType": "CocoStudio.EngineAdapterWrap.CSImageView",
                      "colorB": 255,
                      "colorG": 255,
                      "colorR": 255,
                      "customProperty": "",
                      "flipX": true,
                      "flipY": false,
                      "height": 180,
                      "ignoreSize": false,
                      "layoutParameter": null,
                      "opacity": 255,
                      "positionPercentX": 0.946666658,
                      "positionPercentY": 0.05102041,
                      "positionType": 0,
                      "rotation": 0,
                      "scaleX": 1,
                      "scaleY": 1,
                      "sizePercentX": 0.04,
                      "sizePercentY": 0.9183673,
                      "sizeType": 0,
                      "tag": -92,
                      "touchAble": false,
                      "useMergedTexture": false,
                      "visible": true,
                      "width": 24,
                      "x": 568,
                      "y": 10,
                      "capInsetsHeight": 1,
                      "capInsetsWidth": 1,
                      "capInsetsX": 0,
                      "capInsetsY": 0,
                      "fileName": null,
                      "fileNameData": {
                        "path": "common/mail_border_vertical.png",
                        "plistFile": "",
                        "resourceType": 0
                      },
                      "scale9Enable": false,
                      "scale9Height": 180,
                      "scale9Width": 24
                    }
                  },
                  {
                    "classname": "ImageView",
                    "name": null,
                    "children": [],
                    "options": {
                      "__type": "ImageViewSurrogate:#EditorCommon.JsonModel.Component.GUI",
                      "classname": "ImageView",
                      "name": "7",
                      "ZOrder": 2,
                      "actiontag": 28,
                      "anchorPointX": 0,
                      "anchorPointY": 0,
                      "classType": "CocoStudio.EngineAdapterWrap.CSImageView",
                      "colorB": 255,
                      "colorG": 255,
                      "colorR": 255,
                      "customProperty": "",
                      "flipX": false,
                      "flipY": true,
                      "height": 24,
                      "ignoreSize": true,
                      "layoutParameter": null,
                      "opacity": 255,
                      "positionPercentX": 0.0533333346,
                      "positionPercentY": 0,
                      "positionType": 0,
                      "rotation": 0,
                      "scaleX": 1,
                      "scaleY": 1,
                      "sizePercentX": 0.04,
                      "sizePercentY": 0.122448981,
                      "sizeType": 0,
                      "tag": -93,
                      "touchAble": false,
                      "useMergedTexture": false,
                      "visible": true,
                      "width": 24,
                      "x": 32,
                      "y": 0,
                      "capInsetsHeight": 1,
                      "capInsetsWidth": 1,
                      "capInsetsX": 0,
                      "capInsetsY": 0,
                      "fileName": null,
                      "fileNameData": {
                        "path": "common/mail_border_corner.png",
                        "plistFile": "",
                        "resourceType": 0
                      },
                      "scale9Enable": false,
                      "scale9Height": 24,
                      "scale9Width": 24
                    }
                  },
                  {
                    "classname": "ImageView",
                    "name": null,
                    "children": [],
                    "options": {
                      "__type": "ImageViewSurrogate:#EditorCommon.JsonModel.Component.GUI",
                      "classname": "ImageView",
                      "name": "8",
                      "ZOrder": 0,
                      "actiontag": 29,
                      "anchorPointX": 0.5,
                      "anchorPointY": 0,
                      "classType": "CocoStudio.EngineAdapterWrap.CSImageView",
                      "colorB": 255,
                      "colorG": 255,
                      "colorR": 255,
                      "customProperty": "",
                      "flipX": false,
                      "flipY": true,
                      "height": 24,
                      "ignoreSize": false,
                      "layoutParameter": null,
                      "opacity": 255,
                      "positionPercentX": 0.5,
                      "positionPercentY": 0,
                      "positionType": 0,
                      "rotation": 0,
                      "scaleX": 1,
                      "scaleY": 1,
                      "sizePercentX": 0.863333344,
                      "sizePercentY": 0.122448981,
                      "sizeType": 0,
                      "tag": -91,
                      "touchAble": false,
                      "useMergedTexture": false,
                      "visible": true,
                      "width": 518,
                      "x": 300,
                      "y": 0,
                      "capInsetsHeight": 1,
                      "capInsetsWidth": 1,
                      "capInsetsX": 0,
                      "capInsetsY": 0,
                      "fileName": null,
                      "fileNameData": {
                        "path": "common/mail_border_horizon.png",
                        "plistFile": "",
                        "resourceType": 0
                      },
                      "scale9Enable": false,
                      "scale9Height": 24,
                      "scale9Width": 518
                    }
                  },
                  {
                    "classname": "ImageView",
                    "name": null,
                    "children": [],
                    "options": {
                      "__type": "ImageViewSurrogate:#EditorCommon.JsonModel.Component.GUI",
                      "classname": "ImageView",
                      "name": "9",
                      "ZOrder": 0,
                      "actiontag": 30,
                      "anchorPointX": 1,
                      "anchorPointY": 0,
                      "classType": "CocoStudio.EngineAdapterWrap.CSImageView",
                      "colorB": 255,
                      "colorG": 255,
                      "colorR": 255,
                      "customProperty": "",
                      "flipX": true,
                      "flipY": true,
                      "height": 24,
                      "ignoreSize": true,
                      "layoutParameter": null,
                      "opacity": 255,
                      "positionPercentX": 0.946666658,
                      "positionPercentY": 0,
                      "positionType": 0,
                      "rotation": 0,
                      "scaleX": 1,
                      "scaleY": 1,
                      "sizePercentX": 0.04,
                      "sizePercentY": 0.122448981,
                      "sizeType": 0,
                      "tag": -93,
                      "touchAble": false,
                      "useMergedTexture": false,
                      "visible": true,
                      "width": 24,
                      "x": 568,
                      "y": 0,
                      "capInsetsHeight": 1,
                      "capInsetsWidth": 1,
                      "capInsetsX": 0,
                      "capInsetsY": 0,
                      "fileName": null,
                      "fileNameData": {
                        "path": "common/mail_border_corner.png",
                        "plistFile": "",
                        "resourceType": 0
                      },
                      "scale9Enable": false,
                      "scale9Height": 24,
                      "scale9Width": 24
                    }
                  }
                ],
                "options": {
                  "__type": "PanelSurrogate:#EditorCommon.JsonModel.Component.GUI",
                  "classname": "Panel",
                  "name": "Panel_frame_0",
                  "ZOrder": 0,
                  "actiontag": 19,
                  "anchorPointX": 0,
                  "anchorPointY": 0,
                  "classType": "CocoStudio.EngineAdapterWrap.CSPanel",
                  "colorB": 255,
                  "colorG": 255,
                  "colorR": 255,
                  "customProperty": "",
                  "flipX": false,
                  "flipY": false,
                  "height": 196,
                  "ignoreSize": false,
                  "layoutParameter": null,
                  "opacity": 255,
                  "positionPercentX": 0.03125,
                  "positionPercentY": 0,
                  "positionType": 0,
                  "rotation": 0,
                  "scaleX": 1,
                  "scaleY": 1,
                  "sizePercentX": 0.9375,
                  "sizePercentY": 0.98,
                  "sizeType": 0,
                  "tag": -99,
                  "touchAble": false,
                  "useMergedTexture": false,
                  "visible": true,
                  "width": 600,
                  "x": 20,
                  "y": 0,
                  "adaptScreen": false,
                  "backGroundImage": null,
                  "backGroundImageData": null,
                  "backGroundScale9Enable": false,
                  "bgColorB": 255,
                  "bgColorG": 200,
                  "bgColorOpacity": 100,
                  "bgColorR": 150,
                  "bgEndColorB": 255,
                  "bgEndColorG": 200,
                  "bgEndColorR": 150,
                  "bgStartColorB": 255,
                  "bgStartColorG": 255,
                  "bgStartColorR": 255,
                  "capInsetsHeight": 1,
                  "capInsetsWidth": 1,
                  "capInsetsX": 0,
                  "capInsetsY": 0,
                  "clipAble": false,
                  "colorType": 0,
                  "layoutType": 0,
                  "vectorX": 0,
                  "vectorY": -0.5
                }
              },
              {
                "classname": "Panel",
                "name": null,
                "children": [
                  {
                    "classname": "ImageView",
                    "name": null,
                    "children": [],
                    "options": {
                      "__type": "ImageViewSurrogate:#EditorCommon.JsonModel.Component.GUI",
                      "classname": "ImageView",
                      "name": "ImageView_30333",
                      "ZOrder": 0,
                      "actiontag": 32928,
                      "anchorPointX": 0.5,
                      "anchorPointY": 0.5,
                      "classType": "CocoStudio.EngineAdapterWrap.CSImageView",
                      "colorB": 255,
                      "colorG": 255,
                      "colorR": 255,
                      "customProperty": "",
                      "flipX": false,
                      "flipY": false,
                      "height": 70,
                      "ignoreSize": false,
                      "layoutParameter": null,
                      "opacity": 255,
                      "positionPercentX": 0.5,
                      "positionPercentY": 0.24,
                      "positionType": 0,
                      "rotation": 0,
                      "scaleX": 1,
                      "scaleY": 1,
                      "sizePercentX": 0.8,
                      "sizePercentY": 0.35,
                      "sizeType": 0,
                      "tag": 32206,
                      "touchAble": false,
                      "useMergedTexture": false,
                      "visible": true,
                      "width": 512,
                      "x": 320,
                      "y": 48,
                      "capInsetsHeight": 1,
                      "capInsetsWidth": 1,
                      "capInsetsX": 0,
                      "capInsetsY": 0,
                      "fileName": null,
                      "fileNameData": {
                        "path": "common/common_bg_2.png",
                        "plistFile": "",
                        "resourceType": 0
                      },
                      "scale9Enable": false,
                      "scale9Height": 70,
                      "scale9Width": 512
                    }
                  },
                  {
                    "classname": "ImageView",
                    "name": null,
                    "children": [],
                    "options": {
                      "__type": "ImageViewSurrogate:#EditorCommon.JsonModel.Component.GUI",
                      "classname": "ImageView",
                      "name": "ImageView_30332",
                      "ZOrder": 0,
                      "actiontag": 32927,
                      "anchorPointX": 0,
                      "anchorPointY": 0.5,
                      "classType": "CocoStudio.EngineAdapterWrap.CSImageView",
                      "colorB": 255,
                      "colorG": 255,
                      "colorR": 255,
                      "customProperty": "",
                      "flipX": false,
                      "flipY": false,
                      "height": 36,
                      "ignoreSize": false,
                      "layoutParameter": null,
                      "opacity": 255,
                      "positionPercentX": 0.23125,
                      "positionPercentY": 0.54,
                      "positionType": 0,
                      "rotation": 0,
                      "scaleX": 1,
                      "scaleY": 1,
                      "sizePercentX": 0.4125,
                      "sizePercentY": 0.18,
                      "sizeType": 0,
                      "tag": 32205,
                      "touchAble": false,
                      "useMergedTexture": false,
                      "visible": true,
                      "width": 264,
                      "x": 148,
                      "y": 108,
                      "capInsetsHeight": 1,
                      "capInsetsWidth": 1,
                      "capInsetsX": 0,
                      "capInsetsY": 0,
                      "fileName": null,
                      "fileNameData": {
                        "path": "common/common_bg_2.png",
                        "plistFile": "",
                        "resourceType": 0
                      },
                      "scale9Enable": false,
                      "scale9Height": 36,
                      "scale9Width": 264
                    }
                  }
                ],
                "options": {
                  "__type": "PanelSurrogate:#EditorCommon.JsonModel.Component.GUI",
                  "classname": "Panel",
                  "name": "Panel_30324",
                  "ZOrder": 0,
                  "actiontag": 32923,
                  "anchorPointX": 0,
                  "anchorPointY": 0,
                  "classType": "CocoStudio.EngineAdapterWrap.CSPanel",
                  "colorB": 255,
                  "colorG": 255,
                  "colorR": 255,
                  "customProperty": "",
                  "flipX": false,
                  "flipY": false,
                  "height": 200,
                  "ignoreSize": false,
                  "layoutParameter": null,
                  "opacity": 255,
                  "positionPercentX": 0,
                  "positionPercentY": 0,
                  "positionType": 0,
                  "rotation": 0,
                  "scaleX": 1,
                  "scaleY": 1,
                  "sizePercentX": 1,
                  "sizePercentY": 1,
                  "sizeType": 1,
                  "tag": -99,
                  "touchAble": false,
                  "useMergedTexture": false,
                  "visible": true,
                  "width": 640,
                  "x": 0,
                  "y": 0,
                  "adaptScreen": false,
                  "backGroundImage": null,
                  "backGroundImageData": null,
                  "backGroundScale9Enable": false,
                  "bgColorB": 255,
                  "bgColorG": 200,
                  "bgColorOpacity": 100,
                  "bgColorR": 150,
                  "bgEndColorB": 255,
                  "bgEndColorG": 200,
                  "bgEndColorR": 150,
                  "bgStartColorB": 255,
                  "bgStartColorG": 255,
                  "bgStartColorR": 255,
                  "capInsetsHeight": 1,
                  "capInsetsWidth": 1,
                  "capInsetsX": 0,
                  "capInsetsY": 0,
                  "clipAble": false,
                  "colorType": 0,
                  "layoutType": 0,
                  "vectorX": 0,
                  "vectorY": -0.5
                }
              },
              {
                "classname": "Panel",
                "name": null,
                "children": [
                  {
                    "classname": "Label",
                    "name": null,
                    "children": [],
                    "options": {
                      "__type": "LabelSurrogate:#EditorCommon.JsonModel.Component.GUI",
                      "classname": "Label",
                      "name": "Label_30334",
                      "ZOrder": 0,
                      "actiontag": 32930,
                      "anchorPointX": 0,
                      "anchorPointY": 0.5,
                      "classType": "CocoStudio.EngineAdapterWrap.CSLabel",
                      "colorB": 223,
                      "colorG": 241,
                      "colorR": 245,
                      "customProperty": "",
                      "flipX": false,
                      "flipY": false,
                      "height": 30,
                      "ignoreSize": true,
                      "layoutParameter": null,
                      "opacity": 255,
                      "positionPercentX": 0.2375,
                      "positionPercentY": 0.83,
                      "positionType": 0,
                      "rotation": 0,
                      "scaleX": 1,
                      "scaleY": 1,
                      "sizePercentX": 0.165625,
                      "sizePercentY": 0.15,
                      "sizeType": 0,
                      "tag": 32208,
                      "touchAble": false,
                      "useMergedTexture": false,
                      "visible": true,
                      "width": 106,
                      "x": 152,
                      "y": 166,
                      "areaHeight": 0,
                      "areaWidth": 0,
                      "fontFile": null,
                      "fontName": "微软雅黑",
                      "fontSize": 22,
                      "hAlignment": 0,
                      "text": "Text Label",
                      "touchScaleEnable": false,
                      "vAlignment": 0
                    }
                  },
                  {
                    "classname": "ImageView",
                    "name": null,
                    "children": [],
                    "options": {
                      "__type": "ImageViewSurrogate:#EditorCommon.JsonModel.Component.GUI",
                      "classname": "ImageView",
                      "name": "ImageView_30335",
                      "ZOrder": 0,
                      "actiontag": 32931,
                      "anchorPointX": 0.5,
                      "anchorPointY": 0.5,
                      "classType": "CocoStudio.EngineAdapterWrap.CSImageView",
                      "colorB": 255,
                      "colorG": 255,
                      "colorR": 255,
                      "customProperty": "",
                      "flipX": false,
                      "flipY": false,
                      "height": 76,
                      "ignoreSize": false,
                      "layoutParameter": null,
                      "opacity": 255,
                      "positionPercentX": 0.1625,
                      "positionPercentY": 0.7,
                      "positionType": 0,
                      "rotation": 0,
                      "scaleX": 1,
                      "scaleY": 1,
                      "sizePercentX": 0.11875,
                      "sizePercentY": 0.38,
                      "sizeType": 0,
                      "tag": 32209,
                      "touchAble": false,
                      "useMergedTexture": false,
                      "visible": true,
                      "width": 76,
                      "x": 104,
                      "y": 140,
                      "capInsetsHeight": 1,
                      "capInsetsWidth": 1,
                      "capInsetsX": 0,
                      "capInsetsY": 0,
                      "fileName": null,
                      "fileNameData": {
                        "path": "common/ui_hero_equitFrame.png",
                        "plistFile": "",
                        "resourceType": 0
                      },
                      "scale9Enable": false,
                      "scale9Height": 76,
                      "scale9Width": 76
                    }
                  },
                  {
                    "classname": "Label",
                    "name": null,
                    "children": [],
                    "options": {
                      "__type": "LabelSurrogate:#EditorCommon.JsonModel.Component.GUI",
                      "classname": "Label",
                      "name": "Label_30337",
                      "ZOrder": 0,
                      "actiontag": 32933,
                      "anchorPointX": 0,
                      "anchorPointY": 0.5,
                      "classType": "CocoStudio.EngineAdapterWrap.CSLabel",
                      "colorB": 31,
                      "colorG": 163,
                      "colorR": 255,
                      "customProperty": "",
                      "flipX": false,
                      "flipY": false,
                      "height": 30,
                      "ignoreSize": true,
                      "layoutParameter": null,
                      "opacity": 255,
                      "positionPercentX": 0.2375,
                      "positionPercentY": 0.71,
                      "positionType": 0,
                      "rotation": 0,
                      "scaleX": 1,
                      "scaleY": 1,
                      "sizePercentX": 0.165625,
                      "sizePercentY": 0.15,
                      "sizeType": 0,
                      "tag": 32211,
                      "touchAble": false,
                      "useMergedTexture": false,
                      "visible": true,
                      "width": 106,
                      "x": 152,
                      "y": 142,
                      "areaHeight": 0,
                      "areaWidth": 0,
                      "fontFile": null,
                      "fontName": "微软雅黑",
                      "fontSize": 22,
                      "hAlignment": 0,
                      "text": "Text Label",
                      "touchScaleEnable": false,
                      "vAlignment": 0
                    }
                  },
                  {
                    "classname": "Label",
                    "name": null,
                    "children": [],
                    "options": {
                      "__type": "LabelSurrogate:#EditorCommon.JsonModel.Component.GUI",
                      "classname": "Label",
                      "name": "Label_30338",
                      "ZOrder": 0,
                      "actiontag": 32934,
                      "anchorPointX": 0,
                      "anchorPointY": 0.5,
                      "classType": "CocoStudio.EngineAdapterWrap.CSLabel",
                      "colorB": 223,
                      "colorG": 241,
                      "colorR": 245,
                      "customProperty": "",
                      "flipX": false,
                      "flipY": false,
                      "height": 27,
                      "ignoreSize": true,
                      "layoutParameter": null,
                      "opacity": 255,
                      "positionPercentX": 0.253125,
                      "positionPercentY": 0.54,
                      "positionType": 0,
                      "rotation": 0,
                      "scaleX": 1,
                      "scaleY": 1,
                      "sizePercentX": 0.1484375,
                      "sizePercentY": 0.135,
                      "sizeType": 0,
                      "tag": 32212,
                      "touchAble": false,
                      "useMergedTexture": false,
                      "visible": true,
                      "width": 95,
                      "x": 162,
                      "y": 108,
                      "areaHeight": 0,
                      "areaWidth": 0,
                      "fontFile": null,
                      "fontName": "微软雅黑",
                      "fontSize": 20,
                      "hAlignment": 0,
                      "text": "Text Label",
                      "touchScaleEnable": false,
                      "vAlignment": 0
                    }
                  },
                  {
                    "classname": "ImageView",
                    "name": null,
                    "children": [],
                    "options": {
                      "__type": "ImageViewSurrogate:#EditorCommon.JsonModel.Component.GUI",
                      "classname": "ImageView",
                      "name": "ImageView_30339",
                      "ZOrder": 0,
                      "actiontag": 32935,
                      "anchorPointX": 0.5,
                      "anchorPointY": 0.5,
                      "classType": "CocoStudio.EngineAdapterWrap.CSImageView",
                      "colorB": 255,
                      "colorG": 255,
                      "colorR": 255,
                      "customProperty": "",
                      "flipX": false,
                      "flipY": false,
                      "height": 38,
                      "ignoreSize": true,
                      "layoutParameter": null,
                      "opacity": 255,
                      "positionPercentX": 0.1609375,
                      "positionPercentY": 0.335,
                      "positionType": 0,
                      "rotation": 0,
                      "scaleX": 1,
                      "scaleY": 1,
                      "sizePercentX": 0.05,
                      "sizePercentY": 0.19,
                      "sizeType": 0,
                      "tag": 32213,
                      "touchAble": false,
                      "useMergedTexture": false,
                      "visible": true,
                      "width": 32,
                      "x": 103,
                      "y": 67,
                      "capInsetsHeight": 1,
                      "capInsetsWidth": 1,
                      "capInsetsX": 0,
                      "capInsetsY": 0,
                      "fileName": null,
                      "fileNameData": {
                        "path": "common/alliance_55.png",
                        "plistFile": "",
                        "resourceType": 0
                      },
                      "scale9Enable": false,
                      "scale9Height": 38,
                      "scale9Width": 32
                    }
                  },
                  {
                    "classname": "ImageView",
                    "name": null,
                    "children": [],
                    "options": {
                      "__type": "ImageViewSurrogate:#EditorCommon.JsonModel.Component.GUI",
                      "classname": "ImageView",
                      "name": "ImageView_30340",
                      "ZOrder": 0,
                      "actiontag": 32936,
                      "anchorPointX": 0.5,
                      "anchorPointY": 0.5,
                      "classType": "CocoStudio.EngineAdapterWrap.CSImageView",
                      "colorB": 255,
                      "colorG": 255,
                      "colorR": 255,
                      "customProperty": "",
                      "flipX": false,
                      "flipY": false,
                      "height": 34,
                      "ignoreSize": true,
                      "layoutParameter": null,
                      "opacity": 255,
                      "positionPercentX": 0.1609375,
                      "positionPercentY": 0.155,
                      "positionType": 0,
                      "rotation": 0,
                      "scaleX": 1,
                      "scaleY": 1,
                      "sizePercentX": 0.053125,
                      "sizePercentY": 0.17,
                      "sizeType": 0,
                      "tag": 32214,
                      "touchAble": false,
                      "useMergedTexture": false,
                      "visible": true,
                      "width": 34,
                      "x": 103,
                      "y": 31,
                      "capInsetsHeight": 1,
                      "capInsetsWidth": 1,
                      "capInsetsX": 0,
                      "capInsetsY": 0,
                      "fileName": null,
                      "fileNameData": {
                        "path": "common/power.png",
                        "plistFile": "",
                        "resourceType": 0
                      },
                      "scale9Enable": false,
                      "scale9Height": 34,
                      "scale9Width": 34
                    }
                  },
                  {
                    "classname": "Label",
                    "name": null,
                    "children": [],
                    "options": {
                      "__type": "LabelSurrogate:#EditorCommon.JsonModel.Component.GUI",
                      "classname": "Label",
                      "name": "Label_30341",
                      "ZOrder": 0,
                      "actiontag": 32937,
                      "anchorPointX": 0,
                      "anchorPointY": 0.5,
                      "classType": "CocoStudio.EngineAdapterWrap.CSLabel",
                      "colorB": 223,
                      "colorG": 241,
                      "colorR": 245,
                      "customProperty": "",
                      "flipX": false,
                      "flipY": false,
                      "height": 27,
                      "ignoreSize": true,
                      "layoutParameter": null,
                      "opacity": 255,
                      "positionPercentX": 0.2171875,
                      "positionPercentY": 0.325,
                      "positionType": 0,
                      "rotation": 0,
                      "scaleX": 1,
                      "scaleY": 1,
                      "sizePercentX": 0.1484375,
                      "sizePercentY": 0.135,
                      "sizeType": 0,
                      "tag": 32215,
                      "touchAble": false,
                      "useMergedTexture": false,
                      "visible": true,
                      "width": 95,
                      "x": 139,
                      "y": 65,
                      "areaHeight": 0,
                      "areaWidth": 0,
                      "fontFile": null,
                      "fontName": "微软雅黑",
                      "fontSize": 20,
                      "hAlignment": 0,
                      "text": "Text Label",
                      "touchScaleEnable": false,
                      "vAlignment": 0
                    }
                  },
                  {
                    "classname": "Label",
                    "name": null,
                    "children": [],
                    "options": {
                      "__type": "LabelSurrogate:#EditorCommon.JsonModel.Component.GUI",
                      "classname": "Label",
                      "name": "Label_30341_Copy0",
                      "ZOrder": 0,
                      "actiontag": 32938,
                      "anchorPointX": 0,
                      "anchorPointY": 0.5,
                      "classType": "CocoStudio.EngineAdapterWrap.CSLabel",
                      "colorB": 223,
                      "colorG": 241,
                      "colorR": 245,
                      "customProperty": "",
                      "flipX": false,
                      "flipY": false,
                      "height": 27,
                      "ignoreSize": true,
                      "layoutParameter": null,
                      "opacity": 255,
                      "positionPercentX": 0.2171875,
                      "positionPercentY": 0.155,
                      "positionType": 0,
                      "rotation": 0,
                      "scaleX": 1,
                      "scaleY": 1,
                      "sizePercentX": 0.1484375,
                      "sizePercentY": 0.135,
                      "sizeType": 0,
                      "tag": 32216,
                      "touchAble": false,
                      "useMergedTexture": false,
                      "visible": true,
                      "width": 95,
                      "x": 139,
                      "y": 31,
                      "areaHeight": 0,
                      "areaWidth": 0,
                      "fontFile": null,
                      "fontName": "微软雅黑",
                      "fontSize": 20,
                      "hAlignment": 0,
                      "text": "Text Label",
                      "touchScaleEnable": false,
                      "vAlignment": 0
                    }
                  },
                  {
                    "classname": "Label",
                    "name": null,
                    "children": [],
                    "options": {
                      "__type": "LabelSurrogate:#EditorCommon.JsonModel.Component.GUI",
                      "classname": "Label",
                      "name": "Label_30341_Copy1",
                      "ZOrder": 0,
                      "actiontag": 32939,
                      "anchorPointX": 0,
                      "anchorPointY": 0.5,
                      "classType": "CocoStudio.EngineAdapterWrap.CSLabel",
                      "colorB": 31,
                      "colorG": 163,
                      "colorR": 255,
                      "customProperty": "",
                      "flipX": false,
                      "flipY": false,
                      "height": 27,
                      "ignoreSize": true,
                      "layoutParameter": null,
                      "opacity": 255,
                      "positionPercentX": 0.54375,
                      "positionPercentY": 0.325,
                      "positionType": 0,
                      "rotation": 0,
                      "scaleX": 1,
                      "scaleY": 1,
                      "sizePercentX": 0.1484375,
                      "sizePercentY": 0.135,
                      "sizeType": 0,
                      "tag": 32217,
                      "touchAble": false,
                      "useMergedTexture": false,
                      "visible": true,
                      "width": 95,
                      "x": 348,
                      "y": 65,
                      "areaHeight": 0,
                      "areaWidth": 0,
                      "fontFile": null,
                      "fontName": "微软雅黑",
                      "fontSize": 20,
                      "hAlignment": 0,
                      "text": "Text Label",
                      "touchScaleEnable": false,
                      "vAlignment": 0
                    }
                  },
                  {
                    "classname": "Label",
                    "name": null,
                    "children": [],
                    "options": {
                      "__type": "LabelSurrogate:#EditorCommon.JsonModel.Component.GUI",
                      "classname": "Label",
                      "name": "Label_30341_Copy2",
                      "ZOrder": 0,
                      "actiontag": 32940,
                      "anchorPointX": 0,
                      "anchorPointY": 0.5,
                      "classType": "CocoStudio.EngineAdapterWrap.CSLabel",
                      "colorB": 31,
                      "colorG": 163,
                      "colorR": 255,
                      "customProperty": "",
                      "flipX": false,
                      "flipY": false,
                      "height": 27,
                      "ignoreSize": true,
                      "layoutParameter": null,
                      "opacity": 255,
                      "positionPercentX": 0.54375,
                      "positionPercentY": 0.155,
                      "positionType": 0,
                      "rotation": 0,
                      "scaleX": 1,
                      "scaleY": 1,
                      "sizePercentX": 0.1484375,
                      "sizePercentY": 0.135,
                      "sizeType": 0,
                      "tag": 32218,
                      "touchAble": false,
                      "useMergedTexture": false,
                      "visible": true,
                      "width": 95,
                      "x": 348,
                      "y": 31,
                      "areaHeight": 0,
                      "areaWidth": 0,
                      "fontFile": null,
                      "fontName": "微软雅黑",
                      "fontSize": 20,
                      "hAlignment": 0,
                      "text": "Text Label",
                      "touchScaleEnable": false,
                      "vAlignment": 0
                    }
                  },
                  {
                    "classname": "ImageView",
                    "name": null,
                    "children": [
                      {
                        "classname": "Label",
                        "name": null,
                        "children": [],
                        "options": {
                          "__type": "LabelSurrogate:#EditorCommon.JsonModel.Component.GUI",
                          "classname": "Label",
                          "name": "Label_30346",
                          "ZOrder": 0,
                          "actiontag": 32944,
                          "anchorPointX": 0.5,
                          "anchorPointY": 0.5,
                          "classType": "CocoStudio.EngineAdapterWrap.CSLabel",
                          "colorB": 255,
                          "colorG": 255,
                          "colorR": 255,
                          "customProperty": "",
                          "flipX": false,
                          "flipY": false,
                          "height": 31,
                          "ignoreSize": true,
                          "layoutParameter": null,
                          "opacity": 255,
                          "positionPercentX": 0,
                          "positionPercentY": 0,
                          "positionType": 0,
                          "rotation": 0,
                          "scaleX": 1,
                          "scaleY": 1,
                          "sizePercentX": 0.743589759,
                          "sizePercentY": 0.5344828,
                          "sizeType": 0,
                          "tag": 32222,
                          "touchAble": false,
                          "useMergedTexture": false,
                          "visible": true,
                          "width": 116,
                          "x": 0,
                          "y": 0,
                          "areaHeight": 0,
                          "areaWidth": 0,
                          "fontFile": null,
                          "fontName": "微软雅黑",
                          "fontSize": 24,
                          "hAlignment": 0,
                          "text": "Text Label",
                          "touchScaleEnable": false,
                          "vAlignment": 0
                        }
                      }
                    ],
                    "options": {
                      "__type": "ImageViewSurrogate:#EditorCommon.JsonModel.Component.GUI",
                      "classname": "ImageView",
                      "name": "ImageView_30345_Copy0",
                      "ZOrder": 0,
                      "actiontag": 32943,
                      "anchorPointX": 0.5,
                      "anchorPointY": 0.5,
                      "classType": "CocoStudio.EngineAdapterWrap.CSImageView",
                      "colorB": 255,
                      "colorG": 255,
                      "colorR": 255,
                      "customProperty": "",
                      "flipX": false,
                      "flipY": false,
                      "height": 58,
                      "ignoreSize": false,
                      "layoutParameter": null,
                      "opacity": 255,
                      "positionPercentX": 0.78125,
                      "positionPercentY": 0.625,
                      "positionType": 0,
                      "rotation": 0,
                      "scaleX": 1,
                      "scaleY": 1,
                      "sizePercentX": 0.24375,
                      "sizePercentY": 0.29,
                      "sizeType": 0,
                      "tag": 32221,
                      "touchAble": true,
                      "useMergedTexture": false,
                      "visible": true,
                      "width": 156,
                      "x": 500,
                      "y": 125,
                      "capInsetsHeight": 1,
                      "capInsetsWidth": 1,
                      "capInsetsX": 0,
                      "capInsetsY": 0,
                      "fileName": null,
                      "fileNameData": {
                        "path": "common/button_blue.png",
                        "plistFile": "",
                        "resourceType": 0
                      },
                      "scale9Enable": false,
                      "scale9Height": 58,
                      "scale9Width": 156
                    }
                  }
                ],
                "options": {
                  "__type": "PanelSurrogate:#EditorCommon.JsonModel.Component.GUI",
                  "classname": "Panel",
                  "name": "Panel_30331",
                  "ZOrder": 0,
                  "actiontag": 32929,
                  "anchorPointX": 0,
                  "anchorPointY": 0,
                  "classType": "CocoStudio.EngineAdapterWrap.CSPanel",
                  "colorB": 255,
                  "colorG": 255,
                  "colorR": 255,
                  "customProperty": "",
                  "flipX": false,
                  "flipY": false,
                  "height": 200,
                  "ignoreSize": false,
                  "layoutParameter": null,
                  "opacity": 255,
                  "positionPercentX": 0,
                  "positionPercentY": 0,
                  "positionType": 0,
                  "rotation": 0,
                  "scaleX": 1,
                  "scaleY": 1,
                  "sizePercentX": 1,
                  "sizePercentY": 1,
                  "sizeType": 1,
                  "tag": 32207,
                  "touchAble": false,
                  "useMergedTexture": false,
                  "visible": true,
                  "width": 640,
                  "x": 0,
                  "y": 0,
                  "adaptScreen": false,
                  "backGroundImage": null,
                  "backGroundImageData": null,
                  "backGroundScale9Enable": false,
                  "bgColorB": 255,
                  "bgColorG": 200,
                  "bgColorOpacity": 100,
                  "bgColorR": 150,
                  "bgEndColorB": 255,
                  "bgEndColorG": 200,
                  "bgEndColorR": 150,
                  "bgStartColorB": 255,
                  "bgStartColorG": 255,
                  "bgStartColorR": 255,
                  "capInsetsHeight": 1,
                  "capInsetsWidth": 1,
                  "capInsetsX": 0,
                  "capInsetsY": 0,
                  "clipAble": false,
                  "colorType": 0,
                  "layoutType": 0,
                  "vectorX": 0,
                  "vectorY": -0.5
                }
              }
            ],
            "options": {
              "__type": "PanelSurrogate:#EditorCommon.JsonModel.Component.GUI",
              "classname": "Panel",
              "name": "Panel_30322_Copy1",
              "ZOrder": 0,
              "actiontag": 32922,
              "anchorPointX": 0,
              "anchorPointY": 0,
              "classType": "CocoStudio.EngineAdapterWrap.CSPanel",
              "colorB": 255,
              "colorG": 255,
              "colorR": 255,
              "customProperty": "",
              "flipX": false,
              "flipY": false,
              "height": 200,
              "ignoreSize": false,
              "layoutParameter": {
                "classname": null,
                "name": null,
                "align": 0,
                "gravity": 2,
                "layoutEageType": 0,
                "layoutNormalHorizontal": 0,
                "layoutNormalVertical": 0,
                "layoutParentHorizontal": 0,
                "layoutParentVertical": 0,
                "marginDown": 0,
                "marginLeft": 0,
                "marginRight": 0,
                "marginTop": -650,
                "relativeName": "Panel_30322_Copy1",
                "relativeToName": "ListView_29885",
                "type": 1
              },
              "opacity": 255,
              "positionPercentX": 0,
              "positionPercentY": 0.6941896,
              "positionType": 0,
              "rotation": 0,
              "scaleX": 1,
              "scaleY": 1,
              "sizePercentX": 1,
              "sizePercentY": 0.3058104,
              "sizeType": 0,
              "tag": 32200,
              "touchAble": false,
              "useMergedTexture": false,
              "visible": true,
              "width": 640,
              "x": 0,
              "y": 454,
              "adaptScreen": false,
              "backGroundImage": null,
              "backGroundImageData": null,
              "backGroundScale9Enable": false,
              "bgColorB": 255,
              "bgColorG": 200,
              "bgColorOpacity": 100,
              "bgColorR": 150,
              "bgEndColorB": 255,
              "bgEndColorG": 200,
              "bgEndColorR": 150,
              "bgStartColorB": 255,
              "bgStartColorG": 255,
              "bgStartColorR": 255,
              "capInsetsHeight": 1,
              "capInsetsWidth": 1,
              "capInsetsX": 0,
              "capInsetsY": 0,
              "clipAble": false,
              "colorType": 0,
              "layoutType": 0,
              "vectorX": 0,
              "vectorY": -0.5
            }
          }
        ],
        "options": {
          "__type": "ListViewSurrogate:#EditorCommon.JsonModel.Component.GUI",
          "classname": "ListView",
          "name": "ListView_29885",
          "ZOrder": 0,
          "actiontag": 29885,
          "anchorPointX": 0,
          "anchorPointY": 0,
          "classType": "CocoStudio.EngineAdapterWrap.CSListView",
          "colorB": 255,
          "colorG": 255,
          "colorR": 255,
          "customProperty": "",
          "flipX": false,
          "flipY": false,
          "height": 654,
          "ignoreSize": false,
          "layoutParameter": null,
          "opacity": 255,
          "positionPercentX": 0,
          "positionPercentY": 0.12083333,
          "positionType": 0,
          "rotation": 0,
          "scaleX": 1,
          "scaleY": 1,
          "sizePercentX": 1,
          "sizePercentY": 0.68125,
          "sizeType": 0,
          "tag": -999,
          "touchAble": true,
          "useMergedTexture": false,
          "visible": true,
          "width": 640,
          "x": 0,
          "y": 116,
          "backGroundImage": null,
          "backGroundImageData": null,
          "backGroundScale9Enable": false,
          "bgColorB": 255,
          "bgColorG": 150,
          "bgColorOpacity": 100,
          "bgColorR": 150,
          "bgEndColorB": 255,
          "bgEndColorG": 150,
          "bgEndColorR": 150,
          "bgStartColorB": 255,
          "bgStartColorG": 255,
          "bgStartColorR": 255,
          "bounceEnable": false,
          "capInsetsHeight": 1,
          "capInsetsWidth": 1,
          "capInsetsX": 0,
          "capInsetsY": 0,
          "clipAble": true,
          "colorType": 0,
          "direction": 1,
          "editorClipAble": false,
          "gravity": 0,
          "innerHeight": 0,
          "innerWidth": 0,
          "itemMargin": 0,
          "vectorX": 0,
          "vectorY": -0.5
        }
      }
    ],
    "options": {
      "__type": "PanelSurrogate:#EditorCommon.JsonModel.Component.GUI",
      "classname": "Panel",
      "name": "Panel_main",
      "ZOrder": 0,
      "actiontag": -1,
      "anchorPointX": 0,
      "anchorPointY": 0,
      "classType": "CocoStudio.EngineAdapterWrap.CSPanel",
      "colorB": 255,
      "colorG": 255,
      "colorR": 255,
      "customProperty": "",
      "flipX": false,
      "flipY": false,
      "height": 960,
      "ignoreSize": false,
      "layoutParameter": null,
      "opacity": 255,
      "positionPercentX": 0,
      "positionPercentY": 0,
      "positionType": 0,
      "rotation": 0,
      "scaleX": 1,
      "scaleY": 1,
      "sizePercentX": 0,
      "sizePercentY": 0,
      "sizeType": 0,
      "tag": 29267,
      "touchAble": false,
      "useMergedTexture": false,
      "visible": true,
      "width": 640,
      "x": 0,
      "y": 0,
      "adaptScreen": false,
      "backGroundImage": null,
      "backGroundImageData": null,
      "backGroundScale9Enable": false,
      "bgColorB": 255,
      "bgColorG": 200,
      "bgColorOpacity": 0,
      "bgColorR": 150,
      "bgEndColorB": 255,
      "bgEndColorG": 200,
      "bgEndColorR": 150,
      "bgStartColorB": 255,
      "bgStartColorG": 255,
      "bgStartColorR": 255,
      "capInsetsHeight": 1,
      "capInsetsWidth": 1,
      "capInsetsX": 0,
      "capInsetsY": 0,
      "clipAble": false,
      "colorType": 1,
      "layoutType": 0,
      "vectorX": 0,
      "vectorY": -0.5
    }
  }
}